Workbook

Sheet Sezioni
A1: codice | B1: nominativo | C1: regione | D1: provincia | E1: anno di fondazione | F1: iscritti | G1: sitoweb | H1: email | I1: telefono | J1: PIVA | K1: CF | L1: PEC | M1: indirizzo Sede Legale | N1: Presidente | O1: Componenti | P1: Ente del Terzo Settore | Q1: Organo Di Controllo | R1: Sezione ref. tappa SICAI | S1: Sez. referente regionale
A2: 9299999 | B2: SEZ. PROVA | D2: MI | E2: 1950 | G2: www.sezioneprova.it | H2: sezprova@cai.it | I2: 123456 | L2: sezprova@cai.it | M2: Via Errico Petrella 19, 20124 Milano (MI) | N2: Presidente Sezprova | O2: [{"ruolo": "Delegato Elettivo", "nome": "Francesco", "cognome": "Amendola"}, {"ruolo": "Delegato Elettivo", "nome": "Fabrizio", "cognome": "Savini"}, {"ruolo": "Delegato Elettivo", "nome": "Caio", "cognome": "Sempronio"}, {"ruolo": "Presidente di Sezione", "nome": "Presidente", "cognome": "Sezprova"}]
A3: 9234026 | B3: SEZ. ARSITA | C3: ABRUZZO | D3: TE | E3: 2017 | F3: 204 | H3: arsita@cai.it | I3: 3281182237 | L3: arsita@pec.cai.it | M3: Via San Francesco snc, 64031 Arsita (TE) | N3: Manolo Pierannunzio | O3: [{"ruolo": "Revisore dei conti", "nome": "Catiuscia", "cognome": "Cacciatore"}, {"ruolo": "Consigliere", "nome": "Maria", "cognome": "Scocchia"}, {"ruolo": "Presidente di Sezione", "nome": "Manolo", "cognome": "Pierannunzio"}, {"ruolo": "Consigliere", "nome": "Tony", "cognome": "Orsetti"}, {"ruolo": "Vicepresidente", "nome": "Sandro", "cognome": "Cardone"}]
A4: 9234011 | B4: SEZ. ATESSA | C4: ABRUZZO | D4: CH | E4: 1978 | F4: 197 | G4: organizzazione.cai.it/sez-atessa/ | H4: atessa@cai.it | I4: .3332733526 | L4: atessa@pec.cai.it | M4: Loc. Vallaspra 2, 66041 ATESSA (CH) | N4: Concezio Grappasonno | O4: [{"ruolo": "Segretario", "nome": "Franca", "cognome": "Pasquarelli"}, {"ruolo": "Consigliere", "nome": "Giuseppina", "cognome": "Zaccardi"}, {"ruolo": "Consigliere", "nome": "Ida", "cognome": "D'Alonzo"}, {"ruolo": "Presidente di Sezione", "nome": "Concezio", "cognome": "Grappasonno"}, {"ruolo": "Tesoriere", "nome": "Katiuscia", "cognome": "Cinalli"}, {"ruolo": "Consigliere", "nome": "Maria", "cognome": "De Francesco"}, {"ruolo": "Revisore dei conti", "nome": "Mario", "cognome": "Tinaro"}, {"ruolo": "Vicepresidente", "nome": "Francesca", "cognome": "Tinaro"}]
A5: 9234013 | B5: SEZ. AVEZZANO | C5: ABRUZZO | D5: AQ | E5: 1980 | F5: 383 | G5: https://caiavezzano.it/ | H5: avezzano@cai.it | I5: 3388485199 | K5: 90008240666 | L5: avezzano@pec.cai.it | M5: Via Genserico Fontana 8, 67051 AVEZZANO (AQ) | N5: Antonio Massimiani | O5: [{"ruolo": "Presidente di Sezione", "nome": "Antonio", "cognome": "Massimiani"}, {"ruolo": "Tesoriere", "nome": "Antonio", "cognome": "Massimiani"}, {"ruolo": "Vicepresidente", "nome": "Costanzo", "cognome": "Villa"}, {"ruolo": "Consigliere", "nome": "Enio", "cognome": "Di Lorenzo"}, {"ruolo": "Segretario", "nome": "Gerardo", "cognome": "De Santis"}, {"ruolo": "Consigliere", "nome": "Giacomo", "cognome": "Continenza"}, {"ruolo": "Consigliere", "nome": "Angelo", "cognome": "Cipolloni"}, {"ruolo": "Consigliere", "nome": "Massimo", "cognome": "Gentile"}, {"ruolo": "Consigliere", "nome": "Valeria", "cognome": "Fiocchetti"}, {"ruolo": "Consigliere", "nome": "Walter", "cognome": "Silvestri"}]
A6: 9234024 | B6: SEZ. CARSOLI | C6: ABRUZZO | D6: AQ | E6: 2005 | F6: 234 | H6: carsoli@cai.it | I6: 1 | L6: carsoli@pec.cai.it | M6: Via Mario Galli casella postale 19 snc, 67061 CARSOLI (AQ) | N6: Giampiero Giuliani | O6: [{"ruolo": "Segretario", "nome": "Armando", "cognome": "Felli"}, {"ruolo": "Presidente di Sezione", "nome": "Giampiero", "cognome": "Giuliani"}, {"ruolo": "Consigliere", "nome": "Lorenzo", "cognome": "Augi"}, {"ruolo": "Consigliere", "nome": "Marco", "cognome": "Schiona"}]
A7: 9234015 | B7: SEZ. CASTEL DI SANGRO | C7: ABRUZZO | D7: AQ | E7: 1985 | F7: 177 | G7: organizzazione.cai.it/sez-castel-di-sangro/ | H7: casteldisangro@cai.it | I7: 333-7544405 | K7: 91001930667 | L7: casteldisangro@pec.cai.it | M7: Via del Leone 20, 67031 CASTEL DI SANGRO (AQ) | N7: Franco D'Ambrosio | O7: [{"ruolo": "Presidente di Sezione", "nome": "Franco", "cognome": "D'Ambrosio"}, {"ruolo": "Segretario", "nome": "Giovanni", "cognome": "Torrini"}]
A8: 9234010 | B8: SEZ. CASTELLI | C8: ABRUZZO | D8: TE | E8: 1976 | F8: 103 | G8: organizzazione.cai.it/sez-castelli/ | H8: castelli@cai.it | I8: 3391419402 | K8: 80010070672 | L8: castelli@pec.cai.it | M8: Via Convento 2, 64041 CASTELLI (TE) | N8: Giancarlo Di Pietro | O8: [{"ruolo": "Presidente di Sezione", "nome": "Giancarlo", "cognome": "Di Pietro"}]
A9: 9234001 | B9: SEZ. CHIETI | C9: ABRUZZO | D9: CH | E9: 1872 | F9: 306 | H9: segreteria@caichieti.it | I9: 3494401456 | J9: 00629300690 | K9: 80003750694 | L9: chieti@pec.cai.it | M9: Piazza dei Templi Romani 3, 66100 CHIETI (CH) | N9: Marco Grilli | O9: [{"ruolo": "Consigliere", "nome": "Alessio", "cognome": "Susi"}, {"ruolo": "Delegato Elettivo", "nome": "Igor", "cognome": "Arkhypenko"}, {"ruolo": "Vicepresidente", "nome": "Marcello", "cognome": "Borrone"}, {"ruolo": "Consigliere", "nome": "Gianni", "cognome": "Dal Buono"}, {"ruolo": "Consigliere", "nome": "Davide", "cognome": "Bonelli"}, {"ruolo": "Segretario", "nome": "Giovanni", "cognome": "D'Amico"}, {"ruolo": "Consigliere", "nome": "Francesco", "cognome": "Bonomo"}, {"ruolo": "Revisore dei conti", "nome": "Gianluca", "cognome": "Del Conte"}, {"ruolo": "Consigliere", "nome": "Giorgio", "cognome": "Micoli"}, {"ruolo": "Consigliere", "nome": "Claudia", "cognome": "Marrone"}, {"ruolo": "Presidente di Sezione", "nome": "Marco", "cognome": "Grilli"}, {"ruolo": "Tesoriere", "nome": "Pietro Luigi", "cognome": "Marino"}] | P9: ETS | Q9: No
A10: 9234012 | B10: SEZ. FARA S.MARTINO | C10: ABRUZZO | D10: CH | E10: 1980 | F10: 229 | H10: farasanmartino@cai.it | I10: 3207269364 | J10: 90016790694 | L10: farasanmartino@pec.cai.it | M10: Via Giuseppe Mazzini sn, 66015 FARA SAN MARTINO (CH) | N10: Giovanni Madonna | O10: [{"ruolo": "Revisore dei conti", "nome": "Adamo", "cognome": "D'Achille"}, {"ruolo": "Revisore dei conti", "nome": "Alessandro", "cognome": "Campitelli"}, {"ruolo": "Vicepresidente", "nome": "Antonio", "cognome": "Di Mito"}, {"ruolo": "Presidente di Sezione", "nome": "Giovanni", "cognome": "Madonna"}, {"ruolo": "Consigliere", "nome": "Sergio", "cognome": "Di Giuseppe"}, {"ruolo": "Consigliere", "nome": "Silverio", "cognome": "Di Lello"}, {"ruolo": "Consigliere", "nome": "Mauro", "cognome": "Giancristofaro"}, {"ruolo": "Segretario", "nome": "Gianpaolo", "cognome": "Ricciuti"}, {"ruolo": "Consigliere", "nome": "Pietro", "cognome": "Maesa"}, {"ruolo": "Vicepresidente", "nome": "Francesco", "cognome": "Masciantonio"}, {"ruolo": "Consigliere", "nome": "Michele", "cognome": "D'Orazio"}, {"ruolo": "Consigliere", "nome": "Rita", "cognome": "Amato"}, {"ruolo": "Tesoriere", "nome": "Sante", "cognome": "Liberatoscioli"}]
A11: 9234008 | B11: SEZ. FARINDOLA | C11: ABRUZZO | D11: PE | E11: 1974 | F11: 101 | G11: www.caifarindola.it | H11: farindola@cai.it | I11: 0 | K11: 80019430687 | L11: farindola@pec.cai.it | M11: Via San Rocco 8, 65010 FARINDOLA (PE) | O11: []
A12: 9234007 | B12: SEZ. GUARDIAGRELE | C12: ABRUZZO | D12: CH | E12: 1953 | F12: 269 | H12: guardiagrele@cai.it | K12: 80000600694 | L12: guardiagrele@pec.cai.it | M12: ROMA C/O IACOVELLA CARLO 97, 66016 GUARDIAGRELE (CH) | N12: Antonio Taraborrelli | O12: [{"ruolo": "Delegato Elettivo", "nome": "Pierluigi", "cognome": "Di Prinzio"}, {"ruolo": "Presidente di Sezione", "nome": "Antonio", "cognome": "Taraborrelli"}]
A13: 9234018 | B13: SEZ. ISOLA DEL GRAN SASSO | C13: ABRUZZO | D13: TE | E13: 1987 | F13: 227 | G13: www.caiisola.it | H13: isoladelgransasso@cai.it | I13: 3488577052 | K13: 92008430677 | L13: isoladelgransasso@pec.cai.it | M13: Largo del Torrione 8, 64045 Isola del Gran Sasso d'Italia (TE) | N13: Francesco Trifoni | O13: [{"ruolo": "Consigliere", "nome": "Enza", "cognome": "Lombardi"}, {"ruolo": "Presidente di Sezione", "nome": "Francesco", "cognome": "Trifoni"}, {"ruolo": "Consigliere", "nome": "Marco", "cognome": "Carlini"}, {"ruolo": "Revisore dei conti", "nome": "Christian", "cognome": "Menei"}, {"ruolo": "Consigliere", "nome": "Luca", "cognome": "Morrone"}, {"ruolo": "Revisore dei conti", "nome": "Patrizio", "cognome": "Pallotta"}, {"ruolo": "Revisore dei conti", "nome": "Umberto", "cognome": "Cerquone"}]
A14: 9234002 | B14: SEZ. L'AQUILA | C14: ABRUZZO | D14: AQ | E14: 1874 | F14: 908 | G14: https://cailaquila.it/ | H14: laquila@cai.it | I14: 0862028225 | J14: 00145680666 | K14: 00145680666 | L14: laquila@pec.cai.it | M14: Via Sassa 34, 67100 L'AQUILA (AQ) | N14: Ugo Marinucci | O14: [{"ruolo": "Delegato Elettivo", "nome": "Felice", "cognome": "Flati"}, {"ruolo": "Segretario", "nome": "Francesca", "cognome": "Larocchia"}, {"ruolo": "Segretario", "nome": "Francesca", "cognome": "Larocchia"}, {"ruolo": "Consigliere", "nome": "Giulia", "cognome": "Scaglietta"}, {"ruolo": "Responsabile di segreteria", "nome": "Giulia", "cognome": "Scaglietta"}, {"ruolo": "Responsabile di segreteria", "nome": "Leonardo", "cognome": "Esposito"}, {"ruolo": "Tesoriere", "nome": "Leonardo", "cognome": "Esposito"}, {"ruolo": "Consigliere", "nome": "Corrado", "cognome": "Marsili"}, {"ruolo": "Delegato Elettivo", "nome": "Monica", "cognome": "Maurizio"}, {"ruolo": "Consigliere", "nome": "Gian Luca", "cognome": "Ricciardulli"}, {"ruolo": "Presidente di Sezione", "nome": "Ugo", "cognome": "Marinucci"}, {"ruolo": "Consigliere", "nome": "Valeria", "cognome": "Vizioli"}] | P14: APS - ETS | Q14: No
A15: 9234017 | B15: SEZ. LANCIANO | C15: ABRUZZO | D15: CH | E15: 1986 | F15: 275 | G15: cailanciano.it | H15: lanciano@cai.it | I15: 3271078241 | J15: 90008320690 | K15: 90008320690 | L15: lanciano@pec.cai.it | M15: VIA DEI FRENTANI 43, 66034 LANCIANO (CH) | N15: Catia Manfre' | O15: [{"ruolo": "Responsabile di segreteria", "nome": "Alessandro", "cognome": "Tenaglia"}, {"ruolo": "Revisore dei conti", "nome": "Assunta", "cognome": "Colacioppo"}, {"ruolo": "Presidente di Sezione", "nome": "Catia", "cognome": "Manfre'"}, {"ruolo": "Revisore dei conti", "nome": "Antonio", "cognome": "Scacciavillani"}, {"ruolo": "Consigliere", "nome": "Antonio", "cognome": "Francia"}, {"ruolo": "Segretario", "nome": "Giovanni", "cognome": "Giancristofaro"}, {"ruolo": "Revisore dei conti", "nome": "Gianluca", "cognome": "Iurisci"}, {"ruolo": "Tesoriere", "nome": "Marcella", "cognome": "Simongini"}, {"ruolo": "Delegato Elettivo", "nome": "Martina Ines", "cognome": "Melizzi"}, {"ruolo": "Consigliere", "nome": "Nicola", "cognome": "Luongo"}, {"ruolo": "Tesoriere", "nome": "Pier Franco", "cognome": "Ferrara"}, {"ruolo": "Vicepresidente", "nome": "Fabio", "cognome": "Sireni"}] | P15: APS - ETS | Q15: No
A16: 9234023 | B16: SEZ. LORETO APRUTINO | C16: ABRUZZO | D16: PE | E16: 2006 | F16: 108 | G16: www.cailoretoaprutino.it | H16: loretoaprutino@cai.it | I16: 345 9359339 | J16: 01831370687 | K16: 01831370687 | L16: loretoaprutino@pec.cai.it | M16: Via delle Monache 1, 65014 LORETO APRUTINO (PE) | N16: Arturo Acciavatti | O16: [{"ruolo": "Consigliere", "nome": "Andrea", "cognome": "Acciavatti"}, {"ruolo": "Consigliere", "nome": "Antonietta", "cognome": "Di Girolamo"}, {"ruolo": "Presidente di Sezione", "nome": "Arturo", "cognome": "Acciavatti"}, {"ruolo": "Segretario", "nome": "Daniele", "cognome": "Berardi"}, {"ruolo": "Tesoriere", "nome": "Caterina", "cognome": "Ferri"}, {"ruolo": "Consigliere", "nome": "Daniela", "cognome": "Candeloro"}, {"ruolo": "Consigliere", "nome": "Emanuele", "cognome": "Evangelista"}, {"ruolo": "Consigliere", "nome": "Fabio", "cognome": "Chiappini"}, {"ruolo": "Vicepresidente", "nome": "Fabio", "cognome": "Pellegrini"}]
A17: 9234020 | B17: SEZ. ORTONA | C17: ABRUZZO | D17: CH | E17: 1991 | F17: 146 | G17: organizzazione.cai.it/sez-ortona | H17: ortona@cai.it | I17: 0 | K17: 91002490695 | L17: ortona@pec.cai.it | M17: Via Civiltà del Lavoro angolo Viale Margherita d’Austria, 66026 ORTONA (CH) | N17: Angelo Radoccia | O17: [{"ruolo": "Presidente di Sezione", "nome": "Angelo", "cognome": "Radoccia"}]
A18: 9234006 | B18: SEZ. PENNE | C18: ABRUZZO | D18: PE | E18: 1950 | F18: 212 | G18: caipenne.it | H18: penne@cai.it | I18: +393396207568 | K18: 80014770681 | L18: penne@pec.cai.it | M18: Piazza XX Settembre 10, 65017 PENNE (PE) | N18: Cinzia Abruzzese | O18: [{"ruolo": "Consigliere", "nome": "Antonio", "cognome": "Girasole"}, {"ruolo": "Presidente di Sezione", "nome": "Cinzia", "cognome": "Abruzzese"}, {"ruolo": "Revisore dei conti", "nome": "Diana", "cognome": "Di Simone"}, {"ruolo": "Consigliere", "nome": "Francesca", "cognome": "D'Alberto"}, {"ruolo": "Revisore dei conti", "nome": "Roberto", "cognome": "Giancaterino"}, {"ruolo": "Consigliere", "nome": "Gianluca", "cognome": "D'Andrea"}, {"ruolo": "Segretario", "nome": "Gianluca", "cognome": "D'Andrea"}, {"ruolo": "Vicepresidente", "nome": "Laura", "cognome": "Delli Castelli"}, {"ruolo": "Consigliere", "nome": "Luciano", "cognome": "Schiazza"}, {"ruolo": "Consigliere", "nome": "Milo", "cognome": "Sabatini"}, {"ruolo": "Revisore dei conti", "nome": "Sandro", "cognome": "Rossi"}, {"ruolo": "Consigliere", "nome": "Silvio Sergio", "cognome": "Fortunato"}]
A19: 9234005 | B19: SEZ. PESCARA | C19: ABRUZZO | D19: PE | E19: 1932 | F19: 346 | H19: pescara@cai.it | I19: 085.54621 | J19: 01823940687 | K19: 91041720680 | L19: pescara@pec.cai.it | M19: Via Aldo Moro 15/8, 65129 PESCARA (PE) | N19: Alessandro Galli | O19: [{"ruolo": "Presidente di Sezione", "nome": "Alessandro", "cognome": "Galli"}, {"ruolo": "Delegato Elettivo", "nome": "Elvio", "cognome": "Verna"}]
A20: 9234016 | B20: SEZ. POPOLI | C20: ABRUZZO | D20: PE | E20: 1985 | F20: 190 | H20: popoli@cai.it | I20: 08598599 | L20: popoli@pec.cai.it | M20: Via Guglielmo Marconi c/o Carlo Diodati - Casella Postale 8 20, 65026 POPOLI (PE) | N20: Claudio Di Gregorio | O20: [{"ruolo": "Consigliere", "nome": "Camillo", "cognome": "Di Loreto"}, {"ruolo": "Vicepresidente", "nome": "Carlo", "cognome": "Diodati"}, {"ruolo": "Consigliere", "nome": "Cristina", "cognome": "Salvatore"}, {"ruolo": "Consigliere", "nome": "Davide", "cognome": "Piccioli"}, {"ruolo": "Segretario", "nome": "Donato", "cognome": "Di Benedetto"}, {"ruolo": "Tesoriere", "nome": "Biagio", "cognome": "Di Francescantonio"}, {"ruolo": "Consigliere", "nome": "Venanzio", "cognome": "Golini"}, {"ruolo": "Consigliere", "nome": "Luca", "cognome": "Mariani"}, {"ruolo": "Presidente di Sezione", "nome": "Claudio", "cognome": "Di Gregorio"}] | R20: Sì
A21: 9234004 | B21: SEZ. SULMONA | C21: ABRUZZO | D21: AQ | E21: 1952 | F21: 305 | H21: sulmona@cai.it | I21: 3313742409 | L21: caisulmona@pec.it | M21: GIUSEPPE ANDREA ANGELONI C/OCOMUNITA'MONTANAPELIGNA 11, 67039 SULMONA (AQ) | N21: Nino Restaino | O21: [{"ruolo": "Revisore dei conti", "nome": "Adriano", "cognome": "Marcantonio"}, {"ruolo": "Delegato Elettivo", "nome": "Domenico", "cognome": "Capaldo"}, {"ruolo": "Vicepresidente", "nome": "Domenico", "cognome": "Capaldo"}, {"ruolo": "Tesoriere", "nome": "Giovanni", "cognome": "Tarquini"}, {"ruolo": "Consigliere", "nome": "Maria Pia", "cognome": "Lamberti"}, {"ruolo": "Consigliere", "nome": "Massimo", "cognome": "Mariani"}, {"ruolo": "Presidente di Sezione", "nome": "Nino", "cognome": "Restaino"}, {"ruolo": "Segretario", "nome": "Roberto", "cognome": "Bezzu"}, {"ruolo": "Revisore dei conti", "nome": "Simonetta", "cognome": "Cipriani"}, {"ruolo": "Revisore dei conti", "nome": "Tonino", "cognome": "Proietto"}, {"ruolo": "Consigliere", "nome": "Valter", "cognome": "Adeante"}] | R21: Sì | S21: Sez. referente regionale
A22: 9234003 | B22: SEZ. TERAMO | C22: ABRUZZO | D22: TE | E22: 1914 | F22: 423 | G22: www.caiteramo.it | H22: teramo@cai.it | I22: 0 | J22: 00908080674 | K22: 80006280673 | L22: teramo@pec.cai.it | M22: Via Cona 180, 64100 TERAMO (TE) | N22: Giorgio D'Egidio | O22: [{"ruolo": "Presidente di Sezione", "nome": "Giorgio", "cognome": "D'Egidio"}, {"ruolo": "Vicepresidente", "nome": "Lia", "cognome": "Sisino"}, {"ruolo": "Segretario", "nome": "Mauro", "cognome": "Di Dionisio"}] | P22: Avviata procedura di iscrizione | R22: Sì
A23: 9234027 | B23: SEZ. VAL VIBRATA (MONTI GEMELLI) | C23: ABRUZZO | D23: TE | E23: 2021 | F23: 380 | H23: valvibrata@cai.it | I23: . | L23: valvibrata@pec.cai.it | M23: Via del Lavoro c/o Palestra arrampicata Blue Rock (Centro Sportivo IRIDE) 14, 64014 Martinsicuro (TE) | N23: Davide Francioni | O23: [{"ruolo": "Presidente di Sezione", "nome": "Davide", "cognome": "Francioni"}] | P23: APS - ETS | Q23: No
A24: 9234019 | B24: SEZ. VALLE ROVETO | C24: ABRUZZO | D24: AQ | E24: 1988 | F24: 142 | H24: valleroveto@cai.it | I24: 0863.978152 | K24: 90019100669 | L24: valleroveto@pec.cai.it | M24: Via Ripandelli ex asilo "Città di Genova" snc, 67054 CIVITELLA ROVETO (AQ) | N24: Raffaele Allegritti | O24: [{"ruolo": "Vicepresidente", "nome": "Lucia", "cognome": "Mastropietro"}, {"ruolo": "Consigliere", "nome": "Nicholas", "cognome": "Novelli"}, {"ruolo": "Presidente di Sezione", "nome": "Raffaele", "cognome": "Allegritti"}]
A25: 9234025 | B25: SEZ. VALLELONGA - COPPO DELL'ORSO | C25: ABRUZZO | D25: AQ | E25: 2015 | F25: 150 | G25: Www.coppodellorso.it | H25: coppodellorso@cai.it | I25: 3462473725 | J25: 01797560669 | K25: 9002320662 | L25: vallelonga-coppodellorso@pec.cai.it | M25: Via Garibaldi 1, 67059 Trasacco (AQ) | N25: Odorisio Boccia | O25: [{"ruolo": "Presidente di Sezione", "nome": "Odorisio", "cognome": "Boccia"}] | R25: Sì
A26: 9234022 | B26: SEZ. VASTO | C26: ABRUZZO | D26: CH | E26: 1999 | F26: 273 | G26: wwww.caivasto.it | H26: vasto@cai.it | I26: 3515539370 | K26: 92013420697 | L26: vasto@pec.cai.it | M26: Via delle Cisterne 4, 66054 VASTO (CH) | N26: Francesco Famiani | O26: [{"ruolo": "Presidente di Sezione", "nome": "Francesco", "cognome": "Famiani"}, {"ruolo": "Delegato Elettivo", "nome": "Giuseppe", "cognome": "Celenza"}] | R26: Sì
A27: 9242002 | B27: SEZ. LAGONEGRO | C27: BASILICATA | D27: PZ | E27: 1995 | F27: 202 | G27: www.cailagonegro.com | H27: lagonegro@cai.it | I27: 3481701973 (presidente) | J27: 02143370761 | K27: 91001120764 | L27: lagonegro@pec.cai.it | M27: Viale Roma 9, 85042 LAGONEGRO (PZ) | N27: Pompeo Limongi | O27: [{"ruolo": "Revisore dei conti", "nome": "Antonio", "cognome": "Spaltro"}, {"ruolo": "Delegato Elettivo", "nome": "Graziella", "cognome": "D'Agostino"}, {"ruolo": "Tesoriere", "nome": "Giuseppe", "cognome": "Truncellito"}, {"ruolo": "Consigliere", "nome": "Giuseppe", "cognome": "Truncellito"}, {"ruolo": "Delegato Elettivo", "nome": "Lucia", "cognome": "Mancusi"}, {"ruolo": "Delegato Elettivo", "nome": "Marianna", "cognome": "Ferraro"}, {"ruolo": "Revisore dei conti", "nome": "Marianna", "cognome": "Ferraro"}, {"ruolo": "Revisore dei conti", "nome": "Bruno", "cognome": "Niola"}, {"ruolo": "Presidente di Sezione", "nome": "Pompeo", "cognome": "Limongi"}, {"ruolo": "Consigliere", "nome": "Salvatore", "cognome": "Ledonne"}, {"ruolo": "Consigliere", "nome": "Silvia", "cognome": "Di Taranto"}, {"ruolo": "Consigliere", "nome": "Vincenzo Daniele", "cognome": "Gulfo"}, {"ruolo": "Vicepresidente", "nome": "Vincenzo Daniele", "cognome": "Gulfo"}] | P27: Avviata procedura di iscrizione | R27: Sì
A28: 9242004 | B28: SEZ. MATERA | C28: BASILICATA | D28: MT | E28: 2021 | F28: 279 | G28: www.caimatera.it | H28: matera@cai.it | I28: 3351673705 | L28: matera@pec.cai.it | M28: Via della Croce 1, 75100 Matera (MT) | N28: Margherita Sirritiello | O28: [{"ruolo": "Delegato Elettivo", "nome": "Alessandro", "cognome": "Petrigliano"}, {"ruolo": "Delegato Elettivo", "nome": "Antonio", "cognome": "Chietera"}, {"ruolo": "Revisore dei conti", "nome": "Raffaele", "cognome": "Capoccello"}, {"ruolo": "Consigliere", "nome": "Giacinta", "cognome": "Moliterni"}, {"ruolo": "Delegato Elettivo", "nome": "Elio", "cognome": "Di Bari"}, {"ruolo": "Delegato Elettivo", "nome": "Cosimo", "cognome": "Buono"}, {"ruolo": "Consigliere", "nome": "Felice", "cognome": "Santantonio"}, {"ruolo": "Delegato Elettivo", "nome": "Francesco Paolo", "cognome": "Oliva"}, {"ruolo": "Consigliere", "nome": "Gianfranco", "cognome": "Scalcione"}, {"ruolo": "Consigliere", "nome": "Giulia", "cognome": "Coretti"}, {"ruolo": "Revisore dei conti", "nome": "Luigi", "cognome": "Lanzillotta"}, {"ruolo": "Revisore dei conti", "nome": "Maria Rosaria", "cognome": "Padula"}, {"ruolo": "Consigliere", "nome": "Michele", "cognome": "Colonna"}, {"ruolo": "Presidente di Sezione", "nome": "Margherita", "cognome": "Sirritiello"}, {"ruolo": "Delegato Elettivo", "nome": "Paolo Pancrazio", "cognome": "Baldassarre"}, {"ruolo": "Consigliere", "nome": "Pierfrancesco", "cognome": "Matarazzo"}, {"ruolo": "Consigliere", "nome": "Simona", "cognome": "Di Tomaso"}, {"ruolo": "Consigliere", "nome": "Antonio Vincenzo", "cognome": "Alba"}] | P28: APS - ETS | Q28: No
A29: 9242003 | B29: SEZ. MELFI | C29: BASILICATA | D29: PZ | E29: 2015 | F29: 146 | G29: organizzazione.cai.it/sez-melfi | H29: melfi@cai.it | I29: 3333746453 | L29: melfi@pec.cai.it | M29: Via G. D’Annunzio c/o Autoparking 35, 85025 Melfi (PZ) | N29: Monica Pocchiari | O29: [{"ruolo": "Consigliere", "nome": "Angelo", "cognome": "Bocca"}, {"ruolo": "Tesoriere", "nome": "Adele", "cognome": "Amoroso"}, {"ruolo": "Revisore dei conti", "nome": "Alfredo", "cognome": "Sonnessa"}, {"ruolo": "Delegato Elettivo", "nome": "Pasqualina", "cognome": "Vucci"}, {"ruolo": "Consigliere", "nome": "Monica", "cognome": "Asquino"}, {"ruolo": "Consigliere", "nome": "Carmen", "cognome": "De Angelis"}, {"ruolo": "Segretario", "nome": "Clelia", "cognome": "Carnevale"}, {"ruolo": "Vicepresidente", "nome": "Lucrezia", "cognome": "Croce"}, {"ruolo": "Consigliere", "nome": "Daniele", "cognome": "Simonetti"}, {"ruolo": "Consigliere", "nome": "Marianna", "cognome": "Cefola"}, {"ruolo": "Consigliere", "nome": "Michele", "cognome": "Placido"}, {"ruolo": "Revisore dei conti", "nome": "Michele", "cognome": "Cennamo"}, {"ruolo": "Delegato Elettivo", "nome": "Michelarcangelo", "cognome": "Moscaritolo"}, {"ruolo": "Presidente di Sezione", "nome": "Monica", "cognome": "Pocchiari"}, {"ruolo": "Revisore dei conti", "nome": "Valentina", "cognome": "Loconsolo"}] | P29: ODV - ETS | Q29: No | R29: Sì
A30: 9242001 | B30: SEZ. POTENZA | C30: BASILICATA | D30: PZ | E30: 1990 | F30: 301 | G30: organizzazione.cai.it/sez-potenza | H30: potenza@cai.it | I30: 320 1890881 (Rifugio) | K30: 96031200767 | L30: potenza@pec.cai.it | M30: Via Tirreno Fabbricato A Del Favero, 85100 POTENZA (PZ) | N30: Antonio Aicale | O30: [{"ruolo": "Presidente di Sezione", "nome": "Antonio", "cognome": "Aicale"}, {"ruolo": "Responsabile di segreteria", "nome": "Amedeo", "cognome": "Tucci"}, {"ruolo": "Consigliere", "nome": "Amedeo", "cognome": "Tucci"}, {"ruolo": "Consigliere", "nome": "Angela", "cognome": "Cocuzzo"}, {"ruolo": "Delegato Elettivo", "nome": "Anna", "cognome": "Taurisano"}, {"ruolo": "Delegato Elettivo", "nome": "Carmela", "cognome": "Romaniello"}, {"ruolo": "Revisore dei conti", "nome": "Donatella", "cognome": "Romaniello"}, {"ruolo": "Revisore dei conti", "nome": "Gaetano", "cognome": "Liccione"}, {"ruolo": "Consigliere", "nome": "Giuseppina", "cognome": "Dolce"}, {"ruolo": "Revisore dei conti", "nome": "Livia", "cognome": "Carella"}, {"ruolo": "Segretario", "nome": "Pierluigi", "cognome": "Casella"}, {"ruolo": "Delegato Elettivo", "nome": "Pierluigi", "cognome": "Casella"}, {"ruolo": "Delegato Elettivo", "nome": "Rosalena", "cognome": "Cembrola"}, {"ruolo": "Vicepresidente", "nome": "Franca", "cognome": "Di Trana"}, {"ruolo": "Consigliere", "nome": "Nicola", "cognome": "Pugliese"}, {"ruolo": "Delegato Elettivo", "nome": "Vincenzo", "cognome": "De Palma"}, {"ruolo": "Delegato Elettivo", "nome": "Vito Antonio", "cognome": "Mancusi"}, {"ruolo": "Tesoriere", "nome": "Vito Antonio", "cognome": "Mancusi"}] | P30: ODV - ETS | Q30: No
A31: 9244005 | B31: SEZ. CASTROVILLARI | C31: CALABRIA | D31: CS | E31: 1999 | F31: 348 | G31: www.caicastrovillari.it | H31: castrovillari@cai.it | I31: 334.1005054 | J31: 02934200789 | K31: 94005130789 | L31: castrovillari@pec.cai.it | M31: VIA CAIROLI 80, 87012 CASTROVILLARI (CS) | N31: Carla Primavera | O31: [{"ruolo": "Consigliere", "nome": "Luigi", "cognome": "Arcovio"}, {"ruolo": "Responsabile di segreteria", "nome": "Gaetano", "cognome": "Cersosimo"}, {"ruolo": "Vicepresidente", "nome": "Gaetano", "cognome": "Cersosimo"}, {"ruolo": "Presidente di Sezione", "nome": "Carla", "cognome": "Primavera"}, {"ruolo": "Tesoriere", "nome": "Eugenio Antonio", "cognome": "Iannelli"}, {"ruolo": "Consigliere", "nome": "Luana", "cognome": "Macrini"}, {"ruolo": "Delegato Elettivo", "nome": "Mariarosaria", "cognome": "D'Atri"}, {"ruolo": "Consigliere", "nome": "Paolo", "cognome": "Viceconte"}, {"ruolo": "Revisore dei conti", "nome": "Graziella", "cognome": "Romano"}, {"ruolo": "Revisore dei conti", "nome": "Rossella", "cognome": "Alois"}, {"ruolo": "Consigliere", "nome": "Gaetano", "cognome": "Sangineti"}] | P31: APS - ETS | Q31: No | R31: Sì
A32: 9244004 | B32: SEZ. CATANZARO | C32: CALABRIA | D32: CZ | E32: 1990 | F32: 248 | G32: organizzazione.cai.it/sez-catanzaro | H32: catanzaro@cai.it | I32: 3478051252 | K32: 97020360794 | L32: catanzaro@pec.cai.it | M32: Piazza Duomo 9, 88100 CATANZARO (CZ) | N32: Piergiorgio Iannaccaro | O32: [{"ruolo": "Delegato Elettivo", "nome": "Demetrio", "cognome": "Santone"}, {"ruolo": "Revisore dei conti", "nome": "Rosanna", "cognome": "Riccelli"}, {"ruolo": "Revisore dei conti", "nome": "Alessandro", "cognome": "Gaglianese"}, {"ruolo": "Responsabile di segreteria", "nome": "Marco", "cognome": "Garcea"}, {"ruolo": "Segretario", "nome": "Marco", "cognome": "Garcea"}, {"ruolo": "Presidente di Sezione", "nome": "Piergiorgio", "cognome": "Iannaccaro"}, {"ruolo": "Tesoriere", "nome": "Vitaliano", "cognome": "Oliverio"}] | P32: APS - ETS | Q32: No | R32: Sì
A33: 9244002 | B33: SEZ. COSENZA | C33: CALABRIA | D33: CS | E33: 1990 | F33: 240 | H33: cosenza@cai.it | I33: 098475204 | L33: cosenza@pec.cai.it | M33: Via Casali - Stazione FC, 87100 COSENZA (CS) | N33: Maria Talarico | O33: [{"ruolo": "Presidente di Sezione", "nome": "Maria", "cognome": "Talarico"}] | P33: APS - ETS | Q33: No | R33: Sì | S33: Sez. referente regionale
A34: 9244001 | B34: SEZ. REGGIO CALABRIA | C34: CALABRIA | D34: RC | E34: 1932 | F34: 286 | G34: organizzazione.cai.it/sez-reggio-calabria/ | H34: info@caireggio.it | I34: 0 | K34: 92006240805 | L34: reggiocalabria@pec.cai.it | M34: Via Sbarre Superiore 61/C, 89132 REGGIO CALABRIA (RC) | N34: Giandomenico Posillipo | O34: [{"ruolo": "Consigliere", "nome": "Carmelo", "cognome": "Idone"}, {"ruolo": "Presidente di Sezione", "nome": "Giandomenico", "cognome": "Posillipo"}, {"ruolo": "Segretario", "nome": "Marino", "cognome": "Mollo"}, {"ruolo": "Delegato Elettivo", "nome": "Pino", "cognome": "Perrone"}, {"ruolo": "Vicepresidente", "nome": "Pino", "cognome": "Perrone"}] | P34: APS - ETS | Q34: No | R34: Sì
A35: 9244006 | B35: SEZ. VERBICARO | C35: CALABRIA | D35: CS | E35: 2013 | F35: 146 | H35: caiverbicaro2014@gmail.com | I35: 3356590362 | K35: 96027600780 | L35: verbicaro@pec.cai.it | M35: Via Orologio c/o Centro Educazione Ambientale 11, 87020 VERBICARO (CS) | N35: Alberto Dito | O35: [{"ruolo": "Presidente di Sezione", "nome": "Alberto", "cognome": "Dito"}, {"ruolo": "Consigliere", "nome": "Ennio", "cognome": "Benvenuto"}, {"ruolo": "Vicepresidente", "nome": "Ennio", "cognome": "Benvenuto"}, {"ruolo": "Segretario", "nome": "Francesco", "cognome": "Quattrone"}, {"ruolo": "Segretario", "nome": "Francesco", "cognome": "Quattrone"}, {"ruolo": "Consigliere", "nome": "Carmine", "cognome": "Cirimele"}] | P35: APS - ETS | Q35: Sì
A36: 9238004 | B36: SEZ. AVELLINO | C36: CAMPANIA | D36: AV | E36: 1994 | F36: 325 | G36: www.caiavellino.it | H36: avellino@cai.it | I36: 3274022250 | L36: avellino@pec.cai.it | M36: AntonioTedeschi 18/f, 83100 Avellino (AV) | N36: Alfonso De Cesare | O36: [{"ruolo": "Presidente di Sezione", "nome": "Alfonso", "cognome": "De Cesare"}, {"ruolo": "Consigliere", "nome": "Francesca", "cognome": "Bellucci"}, {"ruolo": "Consigliere", "nome": "Gaetano", "cognome": "Izzo"}, {"ruolo": "Consigliere", "nome": "Giovanni", "cognome": "Rosato"}, {"ruolo": "Revisore dei conti", "nome": "Giulia", "cognome": "Affinito"}, {"ruolo": "Tesoriere", "nome": "Liliana", "cognome": "Cafasso"}, {"ruolo": "Delegato Elettivo", "nome": "Luca Gerardo Pio", "cognome": "Fiorillo"}, {"ruolo": "Consigliere", "nome": "Mario", "cognome": "Delli Priscoli"}, {"ruolo": "Vicepresidente", "nome": "Marco", "cognome": "Figliolia"}, {"ruolo": "Revisore dei conti", "nome": "Maria", "cognome": "Cristallo"}, {"ruolo": "Segretario", "nome": "Maria Agnese", "cognome": "Giordano"}, {"ruolo": "Consigliere", "nome": "Pietro Pio", "cognome": "Liquidato"}, {"ruolo": "Consigliere", "nome": "Roberto", "cognome": "Napolitano"}, {"ruolo": "Revisore dei conti", "nome": "Vito", "cognome": "Abate"}] | P36: APS - ETS | Q36: Sì
A37: 9238008 | B37: SEZ. BENEVENTO | C37: CAMPANIA | D37: BN | E37: 2007 | F37: 407 | H37: benevento@cai.it | I37: 3207406508 | K37: 92047030629 | L37: benevento@pec.cai.it | M37: Via Vitulanese 103, 82100 BENEVENTO (BN) | N37: Berardino Bocchino | O37: [{"ruolo": "Tesoriere", "nome": "Antonio", "cognome": "Giardiello"}, {"ruolo": "Consigliere", "nome": "Antonio", "cognome": "Giardiello"}, {"ruolo": "Presidente di Sezione", "nome": "Berardino", "cognome": "Bocchino"}, {"ruolo": "Revisore dei conti", "nome": "Daniele", "cognome": "Izzo"}, {"ruolo": "Delegato Elettivo", "nome": "Vincenzo", "cognome": "Auletta"}, {"ruolo": "Vicepresidente", "nome": "Vincenzo", "cognome": "Auletta"}, {"ruolo": "Consigliere", "nome": "Anna", "cognome": "Mazzeo"}, {"ruolo": "Consigliere", "nome": "Orazio", "cognome": "Nardone"}, {"ruolo": "Revisore dei conti", "nome": "Piera", "cognome": "Altieri"}, {"ruolo": "Segretario", "nome": "Rossana", "cognome": "D'Arienzo"}, {"ruolo": "Consigliere", "nome": "Rossana", "cognome": "D'Arienzo"}, {"ruolo": "Consigliere", "nome": "Vilma", "cognome": "Tarantino"}, {"ruolo": "Revisore dei conti", "nome": "Umberto", "cognome": "Ficociello"}] | P37: ETS | Q37: Sì
A38: 9238006 | B38: SEZ. CASERTA | C38: CAMPANIA | D38: CE | E38: 1998 | F38: 220 | G38: https://www.caicaserta.it | H38: caserta@cai.it | I38: 3333838602 | J38: 0 | K38: 93067720610 | L38: caserta@pec.cai.it | M38: senza indirizzo, 81100 CASERTA (CE) | N38: Giuseppe Salvatore Spina | O38: [{"ruolo": "Tesoriere", "nome": "Anna", "cognome": "De Lucia"}, {"ruolo": "Consigliere", "nome": "Davide", "cognome": "Bernieri"}, {"ruolo": "Consigliere", "nome": "Ciro", "cognome": "Bologna"}, {"ruolo": "Presidente di Sezione", "nome": "Giuseppe Salvatore", "cognome": "Spina"}, {"ruolo": "Consigliere", "nome": "Antonio", "cognome": "Santillo"}, {"ruolo": "Revisore dei conti", "nome": "Carmine", "cognome": "Venasco"}, {"ruolo": "Consigliere", "nome": "Mary Teresa", "cognome": "Gray"}, {"ruolo": "Revisore dei conti", "nome": "Paola", "cognome": "Formati"}, {"ruolo": "Consigliere", "nome": "Raffaele", "cognome": "Aguzzoli"}, {"ruolo": "Revisore dei conti", "nome": "Rosario", "cognome": "Brocchieri"}, {"ruolo": "Consigliere", "nome": "Terenzio", "cognome": "De Tommaso"}, {"ruolo": "Consigliere", "nome": "Vincenzo", "cognome": "Sollitto"}] | P38: APS - ETS | Q38: Sì
A39: 9238009 | B39: SEZ. CASTELLAMMARE DI STABIA | C39: CAMPANIA | D39: NA | E39: 2009 | F39: 313 | H39: castellammaredistabia@cai.it | L39: castellammaredistabia@pec.cai.it | M39: SAN VINCENZO C/O CPS 15, 80053 CASTELLAMMARE DI STABIA (NA) | N39: Raffaele Luise | O39: [{"ruolo": "Delegato Elettivo", "nome": "Agnese", "cognome": "Sicignano"}, {"ruolo": "Responsabile di segreteria", "nome": "Mariagrazia", "cognome": "De Meo"}, {"ruolo": "Presidente di Sezione", "nome": "Raffaele", "cognome": "Luise"}, {"ruolo": "Vicepresidente", "nome": "Riccardo", "cognome": "Ballo"}]
A40: 9238002 | B40: SEZ. CAVA DEI TIRRENI | C40: CAMPANIA | D40: SA | E40: 1939 | F40: 224 | H40: cavadeitirreni@cai.it | I40: 089 345186 | K40: 95058050659 | L40: cavadeitirreni@pec.cai.it | M40: Corso Mazzini 6, 84013 CAVA DE' TIRRENI (SA) | N40: Lucia Palumbo | O40: [{"ruolo": "Tesoriere", "nome": "Antonio", "cognome": "Mangini"}, {"ruolo": "Vicepresidente", "nome": "Giuseppe", "cognome": "Fortunato"}, {"ruolo": "Presidente di Sezione", "nome": "Lucia", "cognome": "Palumbo"}]
A41: 9238010 | B41: SEZ. MONTE BULGHERIA | C41: CAMPANIA | D41: SA | E41: 2025 | G41: www.caimontebulgheria.it | H41: montebulgheria@cai.it | I41: 0. | K41: 93050060651 | L41: montebulgheria@pec.cai.it | M41: via Vittorio Emanuele 8, 81040 CELLE DI BULGHERIA (SA) | N41: Giuseppe Sorrentino | O41: [{"ruolo": "Segretario", "nome": "Clorinda", "cognome": "Cesaro"}, {"ruolo": "Segretario", "nome": "Clorinda", "cognome": "Cesaro"}, {"ruolo": "Revisore dei conti", "nome": "Giuseppina", "cognome": "Cusati"}, {"ruolo": "Responsabile di segreteria", "nome": "Giovanna", "cognome": "Mazzaro"}, {"ruolo": "Consigliere", "nome": "Giovanna", "cognome": "Magliano"}, {"ruolo": "Consigliere", "nome": "Cristina", "cognome": "Guida"}, {"ruolo": "Presidente di Sezione", "nome": "Giuseppe", "cognome": "Sorrentino"}, {"ruolo": "Revisore dei conti", "nome": "Antonietta", "cognome": "Lamoglie"}, {"ruolo": "Consigliere", "nome": "Marco", "cognome": "Petraglia"}, {"ruolo": "Consigliere", "nome": "Maria", "cognome": "Carbone"}, {"ruolo": "Vicepresidente", "nome": "Paolo", "cognome": "Guida"}, {"ruolo": "Tesoriere", "nome": "Rosanna", "cognome": "Perilli"}, {"ruolo": "Tesoriere", "nome": "Rosanna", "cognome": "Perilli"}, {"ruolo": "Revisore dei conti", "nome": "Rosa Alejandra", "cognome": "Fermin"}]
A42: 9238001 | B42: SEZ. NAPOLI | C42: CAMPANIA | D42: NA | E42: 1871 | F42: 698 | G42: www.cainapoli.it | H42: napoli@cai.it | I42: 081417633 | K42: 80034500639 | L42: napoli@pec.cai.it | M42: VIA ELDORADO CASTEL DELL'OVO SN, 80132 NAPOLI (NA) | N42: Massimo Parisi | O42: [{"ruolo": "Consigliere", "nome": "Carla", "cognome": "Lucini"}, {"ruolo": "Segretario", "nome": "Claudio", "cognome": "Solimene"}, {"ruolo": "Consigliere", "nome": "Ciro", "cognome": "Teodonno"}, {"ruolo": "Revisore dei conti", "nome": "Daniele", "cognome": "Di Meo"}, {"ruolo": "Consigliere", "nome": "Davide", "cognome": "Pronio"}, {"ruolo": "Delegato Elettivo", "nome": "Giovannangelo", "cognome": "De Angelis"}, {"ruolo": "Consigliere", "nome": "Giovannangelo", "cognome": "De Angelis"}, {"ruolo": "Consigliere", "nome": "Umberto", "cognome": "Del Vecchio"}, {"ruolo": "Tesoriere", "nome": "Umberto", "cognome": "Del Vecchio"}, {"ruolo": "Tesoriere", "nome": "Umberto", "cognome": "Del Vecchio"}, {"ruolo": "Revisore dei conti", "nome": "Felice", "cognome": "Cesarano"}, {"ruolo": "Consigliere", "nome": "Giovanni", "cognome": "Lapesa"}, {"ruolo": "Presidente di Sezione", "nome": "Massimo", "cognome": "Parisi"}, {"ruolo": "Vicepresidente", "nome": "Raffaele", "cognome": "Spadaro"}, {"ruolo": "Vicepresidente", "nome": "Raffaele", "cognome": "Spadaro"}, {"ruolo": "Revisore dei conti", "nome": "Ugo", "cognome": "Ferrara"}, {"ruolo": "Consigliere", "nome": "Vito", "cognome": "Forni"}] | P42: APS - ETS | Q42: No
A43: 9238005 | B43: SEZ. PIEDIMONTE MATESE | C43: CAMPANIA | D43: CE | E43: 1998 | F43: 218 | G43: https://www.caipiedimontematese.it/ | H43: piedimontematese@cai.it | I43: 3291837103 | K43: 91004470612 | L43: piedimontematese@pec.cai.it | M43: SAN FRANCESCO 10, 81016 PIEDIMONTE MATESE (CE) | N43: Loredana Loffredo | O43: [{"ruolo": "Tesoriere", "nome": "Matteo", "cognome": "Alberico"}, {"ruolo": "Revisore dei conti", "nome": "Concetta", "cognome": "Moscatiello"}, {"ruolo": "Consigliere", "nome": "Franco", "cognome": "Panella"}, {"ruolo": "Presidente di Sezione", "nome": "Loredana", "cognome": "Loffredo"}, {"ruolo": "Revisore dei conti", "nome": "Maria Doris", "cognome": "Ballarino"}, {"ruolo": "Segretario", "nome": "Rolando", "cognome": "Di Benedetto"}, {"ruolo": "Vicepresidente", "nome": "Ugo", "cognome": "Iannitti"}, {"ruolo": "Revisore dei conti", "nome": "Alessandro", "cognome": "Valle"}]
A44: 9238003 | B44: SEZ. SALERNO | C44: CAMPANIA | D44: SA | E44: 1986 | F44: 609 | G44: https://caisalerno.it/ | H44: info@caisalerno.it | I44: 3338502818 | J44: 02360400655 | K44: 02360400655 | L44: salerno@pec.cai.it | M44: Via Porta di Mare 26, 84121 SALERNO (SA) | N44: Alfredo Nicastri | O44: [{"ruolo": "Presidente di Sezione", "nome": "Alfredo", "cognome": "Nicastri"}, {"ruolo": "Delegato Elettivo", "nome": "Carmine", "cognome": "Nobile"}, {"ruolo": "Responsabile di segreteria", "nome": "Carmine", "cognome": "Nobile"}, {"ruolo": "Vicepresidente", "nome": "Caterina", "cognome": "Ciccarelli"}, {"ruolo": "Revisore dei conti", "nome": "Concetta", "cognome": "Latorre"}, {"ruolo": "Tesoriere", "nome": "Domenico", "cognome": "Ianiro"}, {"ruolo": "Revisore dei conti", "nome": "Donatantonio", "cognome": "Martinelli"}, {"ruolo": "Revisore dei conti", "nome": "Gianfranca", "cognome": "Calenda"}, {"ruolo": "Responsabile di segreteria", "nome": "Luigi", "cognome": "De Santis"}, {"ruolo": "Segretario", "nome": "Mario", "cognome": "Salsano"}] | P44: APS - ETS | Q44: Sì | R44: Sì
A45: 9224016 | B45: SEZ. ARGENTA | C45: EMILIA-ROMAGNA | D45: FE | E45: 1988 | F45: 251 | G45: www.caiargenta.it | H45: caiargenta@virgilio.it | I45: 335267793 | K45: 93091160387 | L45: argenta@pec.cai.it | M45: Via Circonvallazione 21/A, 44011 ARGENTA (FE) | N45: Emanuela Massari | O45: [{"ruolo": "Presidente di Sezione", "nome": "Emanuela", "cognome": "Massari"}, {"ruolo": "Delegato Elettivo", "nome": "Benedetta", "cognome": "Bolognesi"}] | P45: APS - ETS | Q45: No
A46: 9224002 | B46: SEZ. BOLOGNA | C46: EMILIA-ROMAGNA | D46: BO | E46: 1875 | F46: 3286 | H46: bologna@cai.it | I46: 051/234856 | J46: 04229010378 | K46: 80071110375 | L46: bologna@pec.cai.it | M46: Via dei Fornaciai 25/ A, 40129 BOLOGNA (BO) | N46: Gianfranco Ventura Beccari | O46: [{"ruolo": "Consigliere", "nome": "Carlotta", "cognome": "Fusi"}, {"ruolo": "Delegato Elettivo", "nome": "Caterina", "cognome": "Summonte"}, {"ruolo": "Consigliere", "nome": "Caterina", "cognome": "Summonte"}, {"ruolo": "Consigliere", "nome": "Elena", "cognome": "Rostagno"}, {"ruolo": "Consigliere", "nome": "Giacinto", "cognome": "Cimino"}, {"ruolo": "Consigliere", "nome": "Gianluca", "cognome": "Mercatelli"}, {"ruolo": "Vicepresidente", "nome": "Gianluca", "cognome": "Mercatelli"}, {"ruolo": "Delegato Elettivo", "nome": "Giorgio", "cognome": "Colombari"}, {"ruolo": "Revisore dei conti", "nome": "Irene", "cognome": "Vignudelli"}, {"ruolo": "Delegato Elettivo", "nome": "Emanuela", "cognome": "Martelli"}, {"ruolo": "Delegato Elettivo", "nome": "Luigi", "cognome": "Mantovani"}, {"ruolo": "Delegato Elettivo", "nome": "Mario", "cognome": "Romiti"}, {"ruolo": "Revisore dei conti", "nome": "Daniele", "cognome": "Mazzoni"}, {"ruolo": "Consigliere", "nome": "Fabrizio", "cognome": "Melilli"}, {"ruolo": "Delegato Elettivo", "nome": "Nadia", "cognome": "Orsini"}, {"ruolo": "Responsabile di segreteria", "nome": "Roberta", "cognome": "Gavioli"}, {"ruolo": "Delegato Elettivo", "nome": "Stefano", "cognome": "Osti"}, {"ruolo": "Presidente di Sezione", "nome": "Gianfranco", "cognome": "Ventura Beccari"}] | P46: APS - ETS | Q46: Sì
A47: 9224010 | B47: SEZ. CARPI | C47: EMILIA-ROMAGNA | D47: MO | E47: 1945 | F47: 1033 | H47: carpi@cai.it | I47: 0 | J47: 02178870362 | K47: 02178870362 | L47: carpi@pec.cai.it | M47: Via Cuneo C.P.34 51, 41012 CARPI (MO) | N47: Marcello Borsari | O47: [{"ruolo": "Revisore dei conti", "nome": "Chiara", "cognome": "Anceschi"}, {"ruolo": "Consigliere", "nome": "Niccolo'", "cognome": "Bezzecchi"}, {"ruolo": "Consigliere", "nome": "Davide", "cognome": "Caiumi"}, {"ruolo": "Revisore dei conti", "nome": "Dimes", "cognome": "Corradi"}, {"ruolo": "Vicepresidente", "nome": "Marco", "cognome": "Bulgarelli"}, {"ruolo": "Consigliere", "nome": "Marco", "cognome": "Bulgarelli"}, {"ruolo": "Tesoriere", "nome": "Ernestina", "cognome": "Bagnoli"}, {"ruolo": "Consigliere", "nome": "Ernestina", "cognome": "Bagnoli"}, {"ruolo": "Consigliere", "nome": "Giuseppe", "cognome": "Baldessari"}, {"ruolo": "Presidente di Sezione", "nome": "Marcello", "cognome": "Borsari"}, {"ruolo": "Consigliere", "nome": "Nelson", "cognome": "Bova"}, {"ruolo": "Delegato Elettivo", "nome": "Paolo", "cognome": "Lottini"}, {"ruolo": "Consigliere", "nome": "Paolo", "cognome": "Lottini"}, {"ruolo": "Consigliere", "nome": "Patrizia", "cognome": "Po"}, {"ruolo": "Consigliere", "nome": "Maria Luisa", "cognome": "Rebecchi"}, {"ruolo": "Segretario", "nome": "Maria Luisa", "cognome": "Rebecchi"}, {"ruolo": "Revisore dei conti", "nome": "Rina", "cognome": "Lugli"}, {"ruolo": "Delegato Elettivo", "nome": "Rina", "cognome": "Lugli"}, {"ruolo": "Consigliere", "nome": "Fabio", "cognome": "Salvaterra"}] | P47: APS - ETS | Q47: No
A48: 9224017 | B48: SEZ. CASTELFRANCO EMILIA | C48: EMILIA-ROMAGNA | D48: MO | E48: 1994 | F48: 420 | H48: castelfrancoemilia@cai.it | I48: +39 352 089 3571 | K48: 94040280367 | L48: castelfrancoemilia@pec.cai.it | M48: SOLIMEI 19, 41013 CASTELFRANCO EMILIA (MO) | N48: Paolo Barbieri | O48: [{"ruolo": "Segretario", "nome": "Andrea", "cognome": "Mantovani"}, {"ruolo": "Responsabile di segreteria", "nome": "Antonella", "cognome": "Scurani"}, {"ruolo": "Revisore dei conti", "nome": "Serena", "cognome": "Montorsi"}, {"ruolo": "Tesoriere", "nome": "Fabio", "cognome": "Montorsi"}, {"ruolo": "Consigliere", "nome": "Giuseppe", "cognome": "Cavazzoni"}, {"ruolo": "Revisore dei conti", "nome": "Giuliano", "cognome": "Mantovani"}, {"ruolo": "Responsabile di segreteria", "nome": "Giuliano", "cognome": "Mantovani"}, {"ruolo": "Revisore dei conti", "nome": "Massimiliano", "cognome": "Zocchi"}, {"ruolo": "Presidente di Sezione", "nome": "Paolo", "cognome": "Barbieri"}, {"ruolo": "Vicepresidente", "nome": "Simone", "cognome": "Malpezzi"}, {"ruolo": "Delegato Elettivo", "nome": "Gianni", "cognome": "Fabbri"}] | P48: APS - ETS | Q48: No
A49: 9224013 | B49: SEZ. CASTELNOVO NE' MONTI | C49: EMILIA-ROMAGNA | D49: RE | E49: 1983 | F49: 336 | G49: www.caibismantova.it | H49: castelnovonemonti@cai.it | I49: 000000000 | L49: castelnovonemonti@pec.cai.it | M49: Via dei Partigiani Casa del Volontariato 10, 42035 CASTELNOVO NE' MONTI (RE) | N49: Enzo Rizzo | O49: [{"ruolo": "Consigliere", "nome": "Paola", "cognome": "Bacci"}, {"ruolo": "Revisore dei conti", "nome": "Alessandro", "cognome": "Bassoli"}, {"ruolo": "Consigliere", "nome": "Carla", "cognome": "Munari"}, {"ruolo": "Consigliere", "nome": "Pierluigi", "cognome": "Ganapini"}, {"ruolo": "Tesoriere", "nome": "Pierluigi", "cognome": "Ganapini"}, {"ruolo": "Revisore dei conti", "nome": "Lorenza", "cognome": "Lombardi"}, {"ruolo": "Consigliere", "nome": "Luca", "cognome": "Pezzi"}, {"ruolo": "Consigliere", "nome": "Matteo", "cognome": "Cavalletti"}, {"ruolo": "Consigliere", "nome": "Mauro", "cognome": "Moggi"}, {"ruolo": "Delegato Elettivo", "nome": "Gino", "cognome": "Montipo'"}, {"ruolo": "Vicepresidente", "nome": "Gino", "cognome": "Montipo'"}, {"ruolo": "Presidente di Sezione", "nome": "Enzo", "cognome": "Rizzo"}, {"ruolo": "Revisore dei conti", "nome": "Barbara", "cognome": "Ferrari"}, {"ruolo": "Consigliere", "nome": "Roberto", "cognome": "Barbantini"}, {"ruolo": "Consigliere", "nome": "Romano", "cognome": "Marchi"}, {"ruolo": "Consigliere", "nome": "Stefano", "cognome": "Carpi"}, {"ruolo": "Revisore dei conti", "nome": "Enrico", "cognome": "Cecchi"}] | P49: APS - ETS | Q49: Sì
A50: 9224012 | B50: SEZ. CESENA | C50: EMILIA-ROMAGNA | D50: FC | E50: 1965 | F50: 1249 | G50: https://www.caicesena.com/ | H50: cesena@cai.it | I50: 0547661461 | J50: 02605940408 | K50: 81009730409 | L50: cesena@pec.cai.it | M50: Via Cesenatico 5735, 47521 CESENA (FC) | N50: Gino Caimmi | O50: [{"ruolo": "Revisore dei conti", "nome": "Alessandro", "cognome": "Neri"}, {"ruolo": "Consigliere", "nome": "Andrea", "cognome": "Silvagni"}, {"ruolo": "Revisore dei conti", "nome": "Gabriele", "cognome": "Borghetti"}, {"ruolo": "Delegato Elettivo", "nome": "Assunta", "cognome": "Mingione"}, {"ruolo": "Segretario", "nome": "Piero", "cognome": "Bratti"}, {"ruolo": "Responsabile di segreteria", "nome": "Piero", "cognome": "Bratti"}, {"ruolo": "Presidente di Sezione", "nome": "Gino", "cognome": "Caimmi"}, {"ruolo": "Consigliere", "nome": "Luciano", "cognome": "Cola"}, {"ruolo": "Consigliere", "nome": "Diego", "cognome": "Del Vecchio"}, {"ruolo": "Consigliere", "nome": "Ettore", "cognome": "Roverelli"}, {"ruolo": "Consigliere", "nome": "Gerardo", "cognome": "Ambrosini"}, {"ruolo": "Tesoriere", "nome": "Giancarla", "cognome": "Parmeggiani"}, {"ruolo": "Revisore dei conti", "nome": "Michele", "cognome": "La Maida"}, {"ruolo": "Consigliere", "nome": "Marika", "cognome": "Pieri"}, {"ruolo": "Consigliere", "nome": "Sabrina", "cognome": "Lucchi"}, {"ruolo": "Delegato Elettivo", "nome": "Sara", "cognome": "Casini"}, {"ruolo": "Consigliere", "nome": "Samuele", "cognome": "Sacchetti"}, {"ruolo": "Vicepresidente", "nome": "Giuliano", "cognome": "Venturi"}] | P50: APS - ETS | Q50: Sì
A51: 9224011 | B51: SEZ. FAENZA | C51: EMILIA-ROMAGNA | D51: RA | E51: 1947 | F51: 1075 | G51: www.caifenza.it | H51: faenza@cai.it | I51: 0546614404 | J51: 00842950396 | K51: 90000190398 | L51: faenza@pec.cai.it | M51: Corso Matteotti 4/3, 48018 FAENZA (RA) | N51: Giancarlo Buccioli | O51: [{"ruolo": "Consigliere", "nome": "Andrea", "cognome": "Morfino"}, {"ruolo": "Consigliere", "nome": "Bruce", "cognome": "Saggese"}, {"ruolo": "Segretario", "nome": "Claudio", "cognome": "Patuelli"}, {"ruolo": "Consigliere", "nome": "Emma", "cognome": "Ponzi"}, {"ruolo": "Delegato Elettivo", "nome": "Emma", "cognome": "Ponzi"}, {"ruolo": "Vicepresidente", "nome": "Emma", "cognome": "Ponzi"}, {"ruolo": "Delegato Elettivo", "nome": "Ettore", "cognome": "Fabbri"}, {"ruolo": "Presidente di Sezione", "nome": "Giancarlo", "cognome": "Buccioli"}, {"ruolo": "Consigliere", "nome": "Gerardo", "cognome": "Morrone"}, {"ruolo": "Consigliere", "nome": "Maica", "cognome": "Del Toro"}, {"ruolo": "Consigliere", "nome": "Mauro", "cognome": "Renzi"}, {"ruolo": "Consigliere", "nome": "Sara", "cognome": "Reali"}, {"ruolo": "Vicepresidente", "nome": "Maurizio", "cognome": "Solaroli"}, {"ruolo": "Consigliere", "nome": "Maurizio", "cognome": "Solaroli"}] | P51: APS - ETS | Q51: No
A52: 9224006 | B52: SEZ. FERRARA | C52: EMILIA-ROMAGNA | D52: FE | E52: 1927 | F52: 1312 | G52: www.caiferrara.it | H52: ferrara@cai.it | I52: 0532 247236 | J52: 00399570381 | K52: 00399570381 | L52: ferrara@pec.cai.it | M52: Viale Cavour 116, 44100 FERRARA (FE) | N52: Domenico Casellato | O52: [{"ruolo": "Consigliere", "nome": "Maurizio", "cognome": "Fontana"}, {"ruolo": "Delegato Elettivo", "nome": "Claudio", "cognome": "Simoni"}, {"ruolo": "Vicepresidente", "nome": "Claudio", "cognome": "Simoni"}, {"ruolo": "Presidente di Sezione", "nome": "Domenico", "cognome": "Casellato"}, {"ruolo": "Consigliere", "nome": "Elisabetta", "cognome": "Bergonzini"}, {"ruolo": "Consigliere", "nome": "Daniele", "cognome": "Cirelli"}, {"ruolo": "Consigliere", "nome": "Fabiola", "cognome": "Arena"}, {"ruolo": "Consigliere", "nome": "Gabriele", "cognome": "Villa"}, {"ruolo": "Consigliere", "nome": "Giulia", "cognome": "Caselli"}, {"ruolo": "Delegato Elettivo", "nome": "Leonardo", "cognome": "Caselli"}, {"ruolo": "Consigliere", "nome": "Maurizio", "cognome": "Poggioli"}, {"ruolo": "Consigliere", "nome": "Mose'", "cognome": "Menegatti"}, {"ruolo": "Revisore dei conti", "nome": "Nicoletta", "cognome": "Borsetti"}, {"ruolo": "Revisore dei conti", "nome": "Paola", "cognome": "Gozzo"}, {"ruolo": "Consigliere", "nome": "Paolo", "cognome": "Sfarra"}, {"ruolo": "Consigliere", "nome": "Stefano", "cognome": "Fogli"}, {"ruolo": "Consigliere", "nome": "Silvia", "cognome": "Orticelli"}, {"ruolo": "Revisore dei conti", "nome": "Valentino", "cognome": "Bosi"}, {"ruolo": "Delegato Elettivo", "nome": "Valeria", "cognome": "Ferioli"}] | P52: APS - ETS | Q52: No
A53: 9224004 | B53: SEZ. FORLI' | C53: EMILIA-ROMAGNA | D53: FC | E53: 1927 | F53: 676 | H53: forli@cai.it | I53: 3387601333 | K53: 80001810409 | L53: forli@pec.cai.it | M53: Viale dell'Appennino 375, 47121 FORLI' (FC) | N53: Stefano Paradisi | O53: [{"ruolo": "Presidente di Sezione", "nome": "Stefano", "cognome": "Paradisi"}, {"ruolo": "Consigliere", "nome": "Giorgio", "cognome": "Assirelli"}, {"ruolo": "Tesoriere", "nome": "Ivano", "cognome": "Bartolozzi"}, {"ruolo": "Consigliere", "nome": "Martina", "cognome": "Cicognani"}, {"ruolo": "Consigliere", "nome": "Massimo", "cognome": "Petrini"}, {"ruolo": "Delegato Elettivo", "nome": "Luca", "cognome": "Casadei Rossi"}, {"ruolo": "Vicepresidente", "nome": "Luca", "cognome": "Casadei Rossi"}, {"ruolo": "Responsabile di segreteria", "nome": "Sebastian", "cognome": "Castoro"}, {"ruolo": "Vicepresidente", "nome": "Sebastian", "cognome": "Castoro"}] | P53: APS - ETS | Q53: No
A54: 9224005 | B54: SEZ. IMOLA | C54: EMILIA-ROMAGNA | D54: BO | E54: 1927 | F54: 1405 | H54: imola@cai.it | I54: 0 | K54: 90004070372 | L54: imola@pec.cai.it | M54: via Cenni 2, 40026 IMOLA (BO) | N54: Ivano Cobalto | O54: [{"ruolo": "Consigliere", "nome": "Alessandra", "cognome": "Antelli"}, {"ruolo": "Consigliere", "nome": "Alberto", "cognome": "Ricci"}, {"ruolo": "Tesoriere", "nome": "Alessandro", "cognome": "Ambrosini"}, {"ruolo": "Revisore dei conti", "nome": "Stefano", "cognome": "Bedeschi"}, {"ruolo": "Delegato Elettivo", "nome": "Carlo", "cognome": "Machirelli"}, {"ruolo": "Vicepresidente", "nome": "Carlo", "cognome": "Machirelli"}, {"ruolo": "Consigliere", "nome": "Andrea", "cognome": "Dall'Olio"}, {"ruolo": "Consigliere", "nome": "Davide", "cognome": "Bonzi"}, {"ruolo": "Consigliere", "nome": "Elisa", "cognome": "Righetti"}, {"ruolo": "Consigliere", "nome": "Federica", "cognome": "Mimmi"}, {"ruolo": "Presidente di Sezione", "nome": "Ivano", "cognome": "Cobalto"}, {"ruolo": "Delegato Elettivo", "nome": "Loris", "cognome": "Garelli"}, {"ruolo": "Revisore dei conti", "nome": "Manuela", "cognome": "Pederzoli"}, {"ruolo": "Revisore dei conti", "nome": "Mauro", "cognome": "Mimmi"}, {"ruolo": "Consigliere", "nome": "Mirko", "cognome": "Degli Esposti"}, {"ruolo": "Delegato Elettivo", "nome": "Paolo", "cognome": "Mainetti"}, {"ruolo": "Consigliere", "nome": "Paolo", "cognome": "Mainetti"}, {"ruolo": "Consigliere", "nome": "Stefania", "cognome": "Albonetti"}] | P54: APS - ETS | Q54: Sì
A55: 9224019 | B55: SEZ. LUGO | C55: EMILIA-ROMAGNA | D55: RA | E55: 2004 | F55: 540 | G55: https://www.cailugo.it/ | H55: lugo@cai.it | I55: 3703495225 | K55: 91015090391 | L55: lugo@pec.cai.it | M55: GIROLAMO SAVONAROLA 3, 48022 LUGO (RA) | N55: Giulia Tabanelli | O55: [{"ruolo": "Consigliere", "nome": "Corrado", "cognome": "Ceccarelli"}, {"ruolo": "Consigliere", "nome": "Davide", "cognome": "Giovannini"}, {"ruolo": "Consigliere", "nome": "Daniele", "cognome": "Righini"}, {"ruolo": "Consigliere", "nome": "Barbara", "cognome": "Delvecchio"}, {"ruolo": "Revisore dei conti", "nome": "Antonella", "cognome": "Focarelli"}, {"ruolo": "Consigliere", "nome": "Francesco", "cognome": "Casadio"}, {"ruolo": "Consigliere", "nome": "Roberto", "cognome": "Francesconi"}, {"ruolo": "Delegato Elettivo", "nome": "Gianluca", "cognome": "Guerrini"}, {"ruolo": "Presidente di Sezione", "nome": "Giulia", "cognome": "Tabanelli"}, {"ruolo": "Consigliere", "nome": "Laura", "cognome": "Belloni"}, {"ruolo": "Revisore dei conti", "nome": "Paola", "cognome": "Minguzzi"}, {"ruolo": "Revisore dei conti", "nome": "Roberto", "cognome": "Righetti"}, {"ruolo": "Vicepresidente", "nome": "Francesco", "cognome": "Rotundo"}] | P55: APS - ETS | Q55: No
A56: 9224003 | B56: SEZ. MODENA | C56: EMILIA-ROMAGNA | D56: MO | E56: 1875 | F56: 1282 | G56: www.cai.mo.it | H56: modena@cai.it | I56: 0 | J56: 01262720368 | K56: 80014670360 | L56: modena@pec.cai.it | M56: Viale IV Novembre 40, 41100 MODENA (MO) | N56: Enrico Pinelli | O56: [{"ruolo": "Vicepresidente", "nome": "Alberto", "cognome": "Accorsi"}, {"ruolo": "Delegato Elettivo", "nome": "Alberto", "cognome": "Accorsi"}, {"ruolo": "Delegato Elettivo", "nome": "Giuliano", "cognome": "Cavazzuti"}, {"ruolo": "Consigliere", "nome": "Giuliano", "cognome": "Cavazzuti"}, {"ruolo": "Consigliere", "nome": "Fabrizio", "cognome": "Guidicelli"}, {"ruolo": "Consigliere", "nome": "Martino", "cognome": "Pinelli"}, {"ruolo": "Presidente di Sezione", "nome": "Enrico", "cognome": "Pinelli"}, {"ruolo": "Consigliere", "nome": "Romano", "cognome": "Bertugli"}, {"ruolo": "Delegato Elettivo", "nome": "Tomasz Piotr", "cognome": "Turbiarz"}, {"ruolo": "Segretario", "nome": "Tomasz Piotr", "cognome": "Turbiarz"}, {"ruolo": "Tesoriere", "nome": "Fabio", "cognome": "Santoro"}] | P56: APS - ETS | Q56: No | R56: Sì | S56: Sez. referente regionale
A57: 9224001 | B57: SEZ. PARMA | C57: EMILIA-ROMAGNA | D57: PR | E57: 1875 | F57: 2233 | G57: https://caiparma.it/ | H57: parma@cai.it | I57: 0521984901 | J57: 02078830342 | K57: 92038500341 | L57: parma@pec.cai.it | M57: Viale Piacenza 40, 43126 PARMA (PR) | N57: Gian Luca Giovanardi | O57: [{"ruolo": "Consigliere", "nome": "Danilo", "cognome": "Alinovi"}, {"ruolo": "Consigliere", "nome": "Aurora", "cognome": "Scarduzio"}, {"ruolo": "Revisore dei conti", "nome": "Davide", "cognome": "Bino"}, {"ruolo": "Consigliere", "nome": "Carlo Camillo", "cognome": "Prosperi"}, {"ruolo": "Tesoriere", "nome": "Carlo Camillo", "cognome": "Prosperi"}, {"ruolo": "Consigliere", "nome": "Chiara", "cognome": "Orsatti"}, {"ruolo": "Delegato Elettivo", "nome": "Severino", "cognome": "Chiari"}, {"ruolo": "Consigliere", "nome": "Santo", "cognome": "Rampulla"}, {"ruolo": "Revisore dei conti", "nome": "Maria Cristina", "cognome": "Gallina"}, {"ruolo": "Delegato Elettivo", "nome": "Gianfranco", "cognome": "Berte'"}, {"ruolo": "Presidente di Sezione", "nome": "Gian Luca", "cognome": "Giovanardi"}, {"ruolo": "Revisore dei conti", "nome": "Adriana", "cognome": "Grandi"}, {"ruolo": "Consigliere", "nome": "Marco", "cognome": "Tarana"}, {"ruolo": "Consigliere", "nome": "Marco", "cognome": "Iemmi"}, {"ruolo": "Consigliere", "nome": "Valter", "cognome": "Moia"}, {"ruolo": "Delegato Elettivo", "nome": "Valter", "cognome": "Moia"}, {"ruolo": "Segretario", "nome": "Pier Giorgio", "cognome": "Rivara"}, {"ruolo": "Consigliere", "nome": "Pier Giorgio", "cognome": "Rivara"}, {"ruolo": "Consigliere", "nome": "Giovanni", "cognome": "Poggi"}, {"ruolo": "Consigliere", "nome": "Roberto", "cognome": "Zanzucchi"}, {"ruolo": "Delegato Elettivo", "nome": "Roberto", "cognome": "Zanzucchi"}, {"ruolo": "Consigliere", "nome": "Davide", "cognome": "Mori"}] | P57: APS - ETS | Q57: Sì - MONOCRATICO
A58: 9224020 | B58: SEZ. PAVULLO NEL FRIGNANO | C58: EMILIA-ROMAGNA | D58: MO | E58: 2017 | F58: 518 | G58: www.caipavullo.it | H58: pavullonelfrignano@cai.it | I58: 0536793377 | L58: pavullonelfrignano@pec.cai.it | M58: Via Alessandro Ricchi 3, 41026 Pavullo nel Frignano (MO) | N58: Vanni Monti | O58: [{"ruolo": "Consigliere", "nome": "Marco", "cognome": "Albertini"}, {"ruolo": "Vicepresidente", "nome": "Marco", "cognome": "Albertini"}, {"ruolo": "Tesoriere", "nome": "Fabio", "cognome": "Fulgeri"}, {"ruolo": "Consigliere", "nome": "Fabio", "cognome": "Fulgeri"}, {"ruolo": "Consigliere", "nome": "Roberto", "cognome": "Corsini"}, {"ruolo": "Segretario", "nome": "Elisabetta", "cognome": "Bellodi"}, {"ruolo": "Responsabile di segreteria", "nome": "Enrico", "cognome": "Iacoli"}, {"ruolo": "Consigliere", "nome": "Graziano", "cognome": "Boilini"}, {"ruolo": "Consigliere", "nome": "Angelo", "cognome": "Lavacchielli"}, {"ruolo": "Consigliere", "nome": "Leo", "cognome": "Lo Russo"}, {"ruolo": "Consigliere", "nome": "Marcello", "cognome": "Gorzanelli"}, {"ruolo": "Revisore dei conti", "nome": "Marisa", "cognome": "Cintori"}, {"ruolo": "Presidente di Sezione", "nome": "Vanni", "cognome": "Monti"}, {"ruolo": "Revisore dei conti", "nome": "Nadia", "cognome": "Andreoli"}, {"ruolo": "Revisore dei conti", "nome": "Pier Luigi", "cognome": "Vignali"}, {"ruolo": "Delegato Elettivo", "nome": "Serena", "cognome": "Muracchini"}, {"ruolo": "Consigliere", "nome": "Luca", "cognome": "Toni"}] | P58: APS - ETS | Q58: No
A59: 9224007 | B59: SEZ. PIACENZA | C59: EMILIA-ROMAGNA | D59: PC | E59: 1931 | F59: 1013 | H59: info@caipiacenza.it | I59: 0 | J59: 01163430331 | K59: 91003260337 | L59: piacenza@pec.cai.it | M59: STRADONE FARNESE 39, 29121 PIACENZA (PC) | N59: Claudio Faimali | O59: [{"ruolo": "Consigliere", "nome": "Antonio", "cognome": "Caleandro"}, {"ruolo": "Revisore dei conti", "nome": "Bruno", "cognome": "Scotti"}, {"ruolo": "Consigliere", "nome": "Claudio", "cognome": "Faimali"}, {"ruolo": "Presidente di Sezione", "nome": "Claudio", "cognome": "Faimali"}, {"ruolo": "Revisore dei conti", "nome": "Corrado", "cognome": "Capellini"}, {"ruolo": "Consigliere", "nome": "Daniele", "cognome": "Dallari"}, {"ruolo": "Vicepresidente", "nome": "Daniele", "cognome": "Dallari"}, {"ruolo": "Revisore dei conti", "nome": "Davide", "cognome": "Ravoni"}, {"ruolo": "Consigliere", "nome": "Filippo", "cognome": "Rossi"}, {"ruolo": "Delegato Elettivo", "nome": "Massimo", "cognome": "Antoniotti"}, {"ruolo": "Consigliere", "nome": "Massimo", "cognome": "Antoniotti"}, {"ruolo": "Delegato Elettivo", "nome": "Edoardo", "cognome": "Nartelli"}, {"ruolo": "Consigliere", "nome": "Edoardo", "cognome": "Nartelli"}, {"ruolo": "Consigliere", "nome": "Eugenio", "cognome": "Pinotti"}, {"ruolo": "Consigliere", "nome": "Aldo", "cognome": "Scorsoglio"}, {"ruolo": "Consigliere", "nome": "Antonio", "cognome": "Vaccari"}] | P59: APS - ETS | Q59: Sì
A60: 9224018 | B60: SEZ. PORRETTA TERME | C60: EMILIA-ROMAGNA | D60: BO | E60: 1995 | F60: 311 | H60: porrettaterme@cai.it | I60: 0 | K60: 01722351200 | L60: porrettaterme@pec.cai.it | M60: DELLA LIBERTA' 42, 40046 PORRETTA TERME (BO) | N60: Antonella Lizzani | O60: [{"ruolo": "Revisore dei conti", "nome": "Alessandro", "cognome": "Pedretti"}, {"ruolo": "Consigliere", "nome": "Giorgio", "cognome": "Barbato"}, {"ruolo": "Vicepresidente", "nome": "Bruno", "cognome": "Panichi"}, {"ruolo": "Delegato Elettivo", "nome": "Donatella", "cognome": "Filippini"}, {"ruolo": "Consigliere", "nome": "Donatella", "cognome": "Filippini"}, {"ruolo": "Presidente di Sezione", "nome": "Antonella", "cognome": "Lizzani"}, {"ruolo": "Segretario", "nome": "Lucia", "cognome": "Cioni"}, {"ruolo": "Consigliere", "nome": "Fernando", "cognome": "Neri"}, {"ruolo": "Revisore dei conti", "nome": "Stefano", "cognome": "Mazzoni"}, {"ruolo": "Consigliere", "nome": "Ivano", "cognome": "Coli"}, {"ruolo": "Tesoriere", "nome": "Umberto", "cognome": "Neri"}, {"ruolo": "Consigliere", "nome": "Antonio", "cognome": "Ventura"}] | P60: APS - ETS | Q60: Sì
A61: 9224014 | B61: SEZ. RAVENNA | C61: EMILIA-ROMAGNA | D61: RA | E61: 1983 | F61: 863 | H61: ravenna@cai.it | I61: 3757227489 | J61: 01272780394 | K61: 92025500395 | L61: ravenna@pec.cai.it | M61: via Sant'Alberto C/o Centro sociale Le Rose 73, 48123 RAVENNA (RA) | N61: Emiliano Girotti | O61: [{"ruolo": "Consigliere", "nome": "Andrea", "cognome": "Alessi"}, {"ruolo": "Consigliere", "nome": "Alessandro", "cognome": "Pasi"}, {"ruolo": "Consigliere", "nome": "Andrea", "cognome": "Piatesi"}, {"ruolo": "Consigliere", "nome": "Arturo", "cognome": "Mazzoni"}, {"ruolo": "Consigliere", "nome": "Arturo", "cognome": "Mazzoni"}, {"ruolo": "Delegato Elettivo", "nome": "Arturo", "cognome": "Mazzoni"}, {"ruolo": "Consigliere", "nome": "Andrea", "cognome": "Laghi"}, {"ruolo": "Consigliere", "nome": "Andrea", "cognome": "Laghi"}, {"ruolo": "Consigliere", "nome": "Andrea", "cognome": "Laghi"}, {"ruolo": "Revisore dei conti", "nome": "Andrea", "cognome": "Casadio"}, {"ruolo": "Consigliere", "nome": "Filippo", "cognome": "Saladino"}, {"ruolo": "Delegato Elettivo", "nome": "Lucio", "cognome": "Cavalcoli"}, {"ruolo": "Tesoriere", "nome": "Lara", "cognome": "Zannoni"}, {"ruolo": "Consigliere", "nome": "Grazia Margherita", "cognome": "Piolanti"}, {"ruolo": "Presidente di Sezione", "nome": "Emiliano", "cognome": "Girotti"}, {"ruolo": "Revisore dei conti", "nome": "Michele", "cognome": "Colombo"}, {"ruolo": "Revisore dei conti", "nome": "Michele", "cognome": "Colombo"}, {"ruolo": "Segretario", "nome": "Nicola", "cognome": "Falsetti"}, {"ruolo": "Segretario", "nome": "Nicola", "cognome": "Falsetti"}, {"ruolo": "Consigliere", "nome": "Patrizia", "cognome": "Sora"}, {"ruolo": "Vicepresidente", "nome": "Teresa", "cognome": "Cangi"}, {"ruolo": "Vicepresidente", "nome": "Teresa", "cognome": "Cangi"}, {"ruolo": "Revisore dei conti", "nome": "Claudio", "cognome": "Zanzi"}] | P61: APS - ETS | Q61: No
A62: 9224008 | B62: SEZ. REGGIO EMILIA | C62: EMILIA-ROMAGNA | D62: RE | E62: 1875 | F62: 3151 | G62: www.caireggioemilia.it | H62: reggioemilia@cai.it | I62: 0522436685 | J62: 01845040359 | K62: 80022910352 | L62: reggioemilia@pec.cai.it | M62: via Caduti delle Reggiane 1H, 42122 REGGIO EMILIA (RE) | N62: Alberto Fangareggi | O62: [{"ruolo": "Presidente di Sezione", "nome": "Alberto", "cognome": "Fangareggi"}, {"ruolo": "Revisore dei conti", "nome": "Alessandra", "cognome": "Cattani"}, {"ruolo": "Consigliere", "nome": "Alice", "cognome": "Olivi"}, {"ruolo": "Delegato Elettivo", "nome": "Anna Maria", "cognome": "Ferrari"}, {"ruolo": "Delegato Elettivo", "nome": "Anna", "cognome": "Silvi"}, {"ruolo": "Responsabile di segreteria", "nome": "Franca", "cognome": "Raboni"}, {"ruolo": "Consigliere", "nome": "Giordano", "cognome": "Lusuardi"}, {"ruolo": "Consigliere", "nome": "Giorgio", "cognome": "Galli"}, {"ruolo": "Consigliere", "nome": "Isabella", "cognome": "Bovero"}, {"ruolo": "Consigliere", "nome": "Laura", "cognome": "Chimenti"}, {"ruolo": "Delegato Elettivo", "nome": "Enzo", "cognome": "Zannoni"}, {"ruolo": "Consigliere", "nome": "Enzo", "cognome": "Zannoni"}, {"ruolo": "Delegato Elettivo", "nome": "Paola", "cognome": "Malavasi"}, {"ruolo": "Consigliere", "nome": "Marco", "cognome": "Bellei"}, {"ruolo": "Segretario", "nome": "Marco", "cognome": "Bellei"}, {"ruolo": "Consigliere", "nome": "Simona", "cognome": "Morandi"}, {"ruolo": "Tesoriere", "nome": "Paolo", "cognome": "Fontana"}, {"ruolo": "Delegato Elettivo", "nome": "Elio", "cognome": "Pelli"}, {"ruolo": "Consigliere", "nome": "Pietro", "cognome": "Pioppi"}, {"ruolo": "Delegato Elettivo", "nome": "Roberto", "cognome": "Albergucci"}, {"ruolo": "Revisore dei conti", "nome": "Roberto", "cognome": "Albergucci"}, {"ruolo": "Vicepresidente", "nome": "Stefano", "cognome": "Celestini"}, {"ruolo": "Responsabile di segreteria", "nome": "Valeria", "cognome": "Brez"}] | P62: APS - ETS | Q62: No | R62: Sì | S62: Sez. referente regionale
A63: 9224009 | B63: SEZ. RIMINI | C63: EMILIA-ROMAGNA | D63: RN | E63: 1959 | F63: 894 | G63: www.cairimini.it | H63: cairimini@cairimini.it | I63: 3492352679 | J63: 02271740405 | K63: 91026460401 | L63: rimini@pec.cai.it | M63: Via Circonvallazione Meridionale 5/B, 47923 RIMINI (RN) | N63: Massimiliano Zannoni | O63: [{"ruolo": "Revisore dei conti", "nome": "Agnese", "cognome": "Bruschi"}, {"ruolo": "Consigliere", "nome": "Angela", "cognome": "Cedrini"}, {"ruolo": "Tesoriere", "nome": "Giuseppe", "cognome": "Rito"}, {"ruolo": "Consigliere", "nome": "Francesca", "cognome": "Palma"}, {"ruolo": "Delegato Elettivo", "nome": "Giacomo", "cognome": "Carli"}, {"ruolo": "Consigliere", "nome": "Giovanna", "cognome": "Bicchierini"}, {"ruolo": "Consigliere", "nome": "Mauro", "cognome": "Campidelli"}, {"ruolo": "Consigliere", "nome": "Milena", "cognome": "Morri"}, {"ruolo": "Revisore dei conti", "nome": "Mauro", "cognome": "Valentini"}, {"ruolo": "Consigliere", "nome": "Oscar", "cognome": "Del Magno"}, {"ruolo": "Vicepresidente", "nome": "Oscar", "cognome": "Del Magno"}, {"ruolo": "Delegato Elettivo", "nome": "Oscar", "cognome": "Del Magno"}, {"ruolo": "Segretario", "nome": "Samanta", "cognome": "Primavera"}, {"ruolo": "Consigliere", "nome": "Silvano", "cognome": "Migani"}, {"ruolo": "Presidente di Sezione", "nome": "Massimiliano", "cognome": "Zannoni"}, {"ruolo": "Revisore dei conti", "nome": "Gabriele", "cognome": "Valentini"}] | P63: APS - ETS | Q63: No
A64: 9224015 | B64: SEZ. SASSUOLO | C64: EMILIA-ROMAGNA | D64: MO | E64: 1985 | F64: 379 | H64: sassuolo@cai.it | I64: 0536/870273 | J64: 02151290364 | K64: 93004750365 | L64: sassuolo@pec.cai.it | M64: Piazza Risorgimento 52, 41049 SASSUOLO (MO) | N64: Maurizio Preziosi | O64: [{"ruolo": "Vicepresidente", "nome": "Amedeo", "cognome": "Barbolini"}, {"ruolo": "Consigliere", "nome": "Claudio", "cognome": "Fregni"}, {"ruolo": "Consigliere", "nome": "Giovanna", "cognome": "Barbieri"}, {"ruolo": "Consigliere", "nome": "Livio", "cognome": "Benevelli"}, {"ruolo": "Consigliere", "nome": "Marco", "cognome": "Ronchej"}, {"ruolo": "Presidente di Sezione", "nome": "Maurizio", "cognome": "Preziosi"}, {"ruolo": "Consigliere", "nome": "Mirka", "cognome": "Aldini"}, {"ruolo": "Consigliere", "nome": "Roberto", "cognome": "Bettoli"}, {"ruolo": "Delegato Elettivo", "nome": "Maria Virginia", "cognome": "Cappi"}, {"ruolo": "Tesoriere", "nome": "Maria Virginia", "cognome": "Cappi"}, {"ruolo": "Consigliere", "nome": "Maria Virginia", "cognome": "Cappi"}, {"ruolo": "Segretario", "nome": "Maria Virginia", "cognome": "Cappi"}] | P64: APS - ETS | Q64: No
A65: 9200002 | B65: ASSOC.GUIDE ALPINE ITAL. | C65: EXTRA REGIONE | D65: MI | E65: 1979 | F65: 1507 | G65: www.guidealpine.it/ | H65: a.g.a.i@cai.it | I65: 0229414211 | K65: 93002220031 | L65: agai@pec.cai.it | M65: Via Errico Petrella 19, 20124 MILANO (MI) | N65: Martino Peterlongo | O65: [{"ruolo": "Delegato Elettivo", "nome": "Davide", "cognome": "Di Giosaffatte"}, {"ruolo": "Delegato Elettivo", "nome": "Fabrizio", "cognome": "Pina"}, {"ruolo": "Delegato Elettivo", "nome": "Kurt", "cognome": "Walde"}, {"ruolo": "Delegato Elettivo", "nome": "Lorenzo", "cognome": "Cavanna"}, {"ruolo": "Presidente di Sezione", "nome": "Martino", "cognome": "Peterlongo"}]
A66: 9200001 | B66: SEZ. C.A.A.I. | C66: EXTRA REGIONE | D66: MI | E66: 1904 | F66: 267 | H66: caai@cai.it | I66: 0 | L66: caai@pec.cai.it | M66: Via Errico Petrella C/o CAI 19, 20124 MILANO (MI) | N66: Mauro Penasa | O66: [{"ruolo": "Segretario", "nome": "Luca", "cognome": "Baruffini"}, {"ruolo": "Presidente di Sezione", "nome": "Mauro", "cognome": "Penasa"}]
A67: 9200003 | B67: SEZ. C.N.S.A.S. | C67: EXTRA REGIONE | D67: MI | E67: 2011 | F67: 288 | G67: www.cnsas.it | H67: cnsas@cai.it | I67: 0229530433 | J67: 12172820156 | K67: 10090520155 | L67: cnsas@pec.cai.it | M67: Via Errico Petrella 19, 20124 MILANO (MI) | N67: Maurizio Dellantonio | O67: [{"ruolo": "Delegato Elettivo", "nome": "Adriano", "cognome": "Favre"}, {"ruolo": "Delegato Elettivo", "nome": "Alessandro Giuseppe", "cognome": "Molinu"}, {"ruolo": "Delegato Elettivo", "nome": "Andrea", "cognome": "Placido"}, {"ruolo": "Delegato Elettivo", "nome": "Agrippino", "cognome": "Giostra"}, {"ruolo": "Delegato Elettivo", "nome": "Alex", "cognome": "Barattin"}, {"ruolo": "Delegato Elettivo", "nome": "Roberto", "cognome": "Bolza"}, {"ruolo": "Delegato Elettivo", "nome": "Corrado", "cognome": "Pesci"}, {"ruolo": "Delegato Elettivo", "nome": "Luca Cosimo", "cognome": "Franzese"}, {"ruolo": "Delegato Elettivo", "nome": "Giorgio", "cognome": "Bisagna"}, {"ruolo": "Delegato Elettivo", "nome": "Alberto", "cognome": "Gabutti"}, {"ruolo": "Delegato Elettivo", "nome": "Leonardo", "cognome": "La Pica"}, {"ruolo": "Delegato Elettivo", "nome": "Fabrizio", "cognome": "Masella"}, {"ruolo": "Presidente di Sezione", "nome": "Maurizio", "cognome": "Dellantonio"}, {"ruolo": "Delegato Elettivo", "nome": "Renato", "cognome": "Tessari"}]
A68: 9222026 | B68: SEZ. CERVIGNANO DEL FRIULI | C68: FRIULI-VENEZIA GIULIA | D68: UD | E68: 1999 | F68: 517 | G68: https://www.caicervignano.it/ | H68: cervignanodelfriuli@cai.it | I68: 0431364228 | J68: 02131100303 | K68: 02131100303 | L68: cervignanodelfriuli@pec.cai.it | M68: Via Giuseppe Garibaldi 18, 33052 CERVIGNANO DEL FRIULI (UD) | N68: Ivano Roppa | O68: [{"ruolo": "Consigliere", "nome": "Carlo", "cognome": "Vrech"}, {"ruolo": "Segretario", "nome": "Paola", "cognome": "Facchinetti"}, {"ruolo": "Tesoriere", "nome": "Gabriella", "cognome": "Dreossi"}, {"ruolo": "Presidente di Sezione", "nome": "Ivano", "cognome": "Roppa"}, {"ruolo": "Consigliere", "nome": "Ivan", "cognome": "Snidero"}, {"ruolo": "Consigliere", "nome": "Leonardo Giuseppe", "cognome": "Colloca"}, {"ruolo": "Delegato Elettivo", "nome": "Luca", "cognome": "Piliego"}, {"ruolo": "Consigliere", "nome": "Marinella", "cognome": "Amoruso"}, {"ruolo": "Consigliere", "nome": "Nicola", "cognome": "Venica"}, {"ruolo": "Vicepresidente", "nome": "Nevio", "cognome": "Medeot"}] | P68: APS - ETS | Q68: No
A69: 9222016 | B69: SEZ. CIMOLAIS | C69: FRIULI-VENEZIA GIULIA | D69: PN | E69: 1971 | F69: 218 | H69: cimolais@cai.it | I69: 042787267 | L69: cimolais@pec.cai.it | M69: ROMA 13, 33080 CIMOLAIS (PN) | N69: Giulia Filippin | O69: [{"ruolo": "Presidente di Sezione", "nome": "Giulia", "cognome": "Filippin"}]
A70: 9222014 | B70: SEZ. CIVIDALE DEL FRIULI | C70: FRIULI-VENEZIA GIULIA | D70: UD | E70: 1964 | F70: 1126 | H70: cividaledelfriuli@cai.it | I70: 0432700096 | J70: 01957320300 | K70: 80024830301 | L70: cividaledelfriuli@pec.cai.it | M70: VIA CARRARIA 101, 33043 CIVIDALE DEL FRIULI (UD) | N70: Claudio Busolini | O70: [{"ruolo": "Delegato Elettivo", "nome": "Christian", "cognome": "Olivo"}, {"ruolo": "Presidente di Sezione", "nome": "Claudio", "cognome": "Busolini"}, {"ruolo": "Delegato Elettivo", "nome": "Giulia", "cognome": "Zanuttigh"}, {"ruolo": "Vicepresidente", "nome": "Paolo", "cognome": "Cozzarolo"}] | R70: Sì
A71: 9222015 | B71: SEZ. CLAUT | C71: FRIULI-VENEZIA GIULIA | D71: PN | E71: 1969 | F71: 244 | H71: claut@cai.it | I71: 0427878453 | J71: 01415450939 | K71: 90001580969 | L71: claut@pec.cai.it | M71: Viale Don Pietro Bortolotto 55, 33080 CLAUT (PN) | N71: Antonella Beacco | O71: [{"ruolo": "Consigliere", "nome": "Albino", "cognome": "Rinaldo"}, {"ruolo": "Presidente di Sezione", "nome": "Antonella", "cognome": "Beacco"}, {"ruolo": "Delegato Elettivo", "nome": "Carlo", "cognome": "Martini"}, {"ruolo": "Vicepresidente", "nome": "Carlo", "cognome": "Martini"}, {"ruolo": "Consigliere", "nome": "Serena", "cognome": "Filipputti"}, {"ruolo": "Consigliere", "nome": "Alessandra", "cognome": "Bellitto"}, {"ruolo": "Revisore dei conti", "nome": "Ferruccio", "cognome": "Martini"}, {"ruolo": "Revisore dei conti", "nome": "Ugo", "cognome": "Cerretani"}, {"ruolo": "Segretario", "nome": "Danilo", "cognome": "Bettin"}, {"ruolo": "Consigliere", "nome": "Sergio", "cognome": "Buricelli"}, {"ruolo": "Consigliere", "nome": "Silvano", "cognome": "Frattino"}, {"ruolo": "Responsabile di segreteria", "nome": "Susanna", "cognome": "Beacco"}, {"ruolo": "Revisore dei conti", "nome": "Teresa", "cognome": "Beacco"}]
A72: 9222027 | B72: SEZ. CODROIPO | C72: FRIULI-VENEZIA GIULIA | D72: UD | E72: 2001 | F72: 603 | G72: www.caicodroipo.it | H72: codroipo@cai.it | I72: 0432 900 355 | K72: 94080370300 | L72: codroipo@pec.cai.it | M72: Via Circonvallazione Sud 25, 33033 CODROIPO (UD) | N72: Roberto Dattilo | O72: [{"ruolo": "Presidente di Sezione", "nome": "Roberto", "cognome": "Dattilo"}, {"ruolo": "Tesoriere", "nome": "Sonja", "cognome": "Galassi"}, {"ruolo": "Delegato Elettivo", "nome": "Sonja", "cognome": "Galassi"}] | P72: APS - ETS | Q72: No
A73: 9222022 | B73: SEZ. FORNI AVOLTRI | C73: FRIULI-VENEZIA GIULIA | D73: UD | E73: 1982 | F73: 353 | H73: forniavoltri@cai.it | I73: 3357163890 | K73: 93002460306 | L73: forniavoltri@pec.cai.it | M73: Via Como Casermetta Romanin, 33020 FORNI AVOLTRI (UD) | N73: Fabio Del Fabbro | O73: [{"ruolo": "Presidente di Sezione", "nome": "Fabio", "cognome": "Del Fabbro"}, {"ruolo": "Vicepresidente", "nome": "Renato", "cognome": "Romanin"}, {"ruolo": "Consigliere", "nome": "Sergio", "cognome": "Disnan"}, {"ruolo": "Delegato Elettivo", "nome": "Sergio", "cognome": "Disnan"}] | P73: Avviata procedura di iscrizione | R73: Sì
A74: 9222021 | B74: SEZ. FORNI DI SOPRA | C74: FRIULI-VENEZIA GIULIA | D74: UD | E74: 1982 | F74: 481 | H74: fornidisopra@cai.it | I74: 0 | K74: 01088800303 | L74: fornidisopra@pec.cai.it | M74: NAZIONALE 206, 33024 FORNI DI SOPRA (UD) | N74: Alberto Antoniacomi | O74: [{"ruolo": "Presidente di Sezione", "nome": "Alberto", "cognome": "Antoniacomi"}, {"ruolo": "Consigliere", "nome": "Paola", "cognome": "Cosolo"}, {"ruolo": "Consigliere", "nome": "Elisa", "cognome": "Temil"}, {"ruolo": "Delegato Elettivo", "nome": "Elisa", "cognome": "Temil"}, {"ruolo": "Revisore dei conti", "nome": "Luca", "cognome": "Furlan"}, {"ruolo": "Revisore dei conti", "nome": "Laura", "cognome": "Agnese"}, {"ruolo": "Consigliere", "nome": "Lorenzo", "cognome": "D'Andrea"}, {"ruolo": "Consigliere", "nome": "Marco", "cognome": "Chinese"}, {"ruolo": "Segretario", "nome": "Martina", "cognome": "Costini"}, {"ruolo": "Consigliere", "nome": "Mattia", "cognome": "Lozza"}, {"ruolo": "Consigliere", "nome": "Rolando", "cognome": "Nassivera"}, {"ruolo": "Revisore dei conti", "nome": "Sara", "cognome": "Polo"}] | P74: APS - ETS | Q74: No
A75: 9222007 | B75: SEZ. GEMONA DEL FRIULI | C75: FRIULI-VENEZIA GIULIA | D75: UD | E75: 1927 | F75: 594 | H75: gemonadelfriuli@cai.it | I75: 0 | K75: 91001770303 | L75: gemonadelfriuli@pec.cai.it | M75: IV NOVEMBRE 38, 33013 GEMONA DEL FRIULI (UD) | N75: Ivan Blasotti | O75: [{"ruolo": "Presidente di Sezione", "nome": "Ivan", "cognome": "Blasotti"}, {"ruolo": "Delegato Elettivo", "nome": "Paolo", "cognome": "Giovanelli"}] | P75: APS - ETS | Q75: No
A76: 9222005 | B76: SEZ. GORIZIA | C76: FRIULI-VENEZIA GIULIA | D76: GO | E76: 1883 | F76: 909 | H76: gorizia@cai.it | I76: 048182505 | K76: 80000410318 | L76: gorizia@pec.cai.it | M76: Via Rossini 13, 34170 GORIZIA (GO) | N76: Fabio Algadeni | O76: [{"ruolo": "Delegato Elettivo", "nome": "Bruno", "cognome": "Ballare'"}, {"ruolo": "Consigliere", "nome": "Bruno", "cognome": "Ballare'"}, {"ruolo": "Consigliere", "nome": "Chiara", "cognome": "Glessi"}, {"ruolo": "Revisore dei conti", "nome": "Claudio", "cognome": "Poian"}, {"ruolo": "Delegato Elettivo", "nome": "Maurizio", "cognome": "Quaglia"}, {"ruolo": "Presidente di Sezione", "nome": "Fabio", "cognome": "Algadeni"}, {"ruolo": "Segretario", "nome": "Franco", "cognome": "Chiandussi"}, {"ruolo": "Vicepresidente", "nome": "Giusto", "cognome": "Gorlato"}, {"ruolo": "Consigliere", "nome": "Liliana", "cognome": "Foghin"}, {"ruolo": "Consigliere", "nome": "Loris", "cognome": "Tulisso"}, {"ruolo": "Consigliere", "nome": "Stefano", "cognome": "Battorti"}, {"ruolo": "Revisore dei conti", "nome": "Oliviero", "cognome": "Furlan"}, {"ruolo": "Revisore dei conti", "nome": "Paolo", "cognome": "Geotti"}, {"ruolo": "Tesoriere", "nome": "Sabina", "cognome": "Mari"}, {"ruolo": "Consigliere", "nome": "Stefano", "cognome": "Cassani"}] | P76: APS - ETS | Q76: No | R76: Sì
A77: 9222008 | B77: SEZ. MANIAGO | C77: FRIULI-VENEZIA GIULIA | D77: PN | E77: 1947 | F77: 367 | G77: organizzazione.cai.it/sez-maniago/ | H77: maniago@cai.it | I77: 0 | K77: 81005590930 | L77: maniago@pec.cai.it | M77: COLVERA 99/A, 33085 MANIAGO (PN) | N77: Gianni Valguarnera | O77: [{"ruolo": "Delegato Elettivo", "nome": "Nicola", "cognome": "Bonavolta"}, {"ruolo": "Presidente di Sezione", "nome": "Gianni", "cognome": "Valguarnera"}]
A78: 9222025 | B78: SEZ. MANZANO | C78: FRIULI-VENEZIA GIULIA | D78: UD | E78: 1993 | F78: 239 | H78: manzano@cai.it | I78: 0 | J78: 94004860303 | K78: 94004860303 | L78: manzano@pec.cai.it | M78: ZORUTTI 21, 33044 MANZANO (UD) | N78: Edi Pezzarini | O78: [{"ruolo": "Consigliere", "nome": "Alessandra", "cognome": "Magrino"}, {"ruolo": "Vicepresidente", "nome": "Mauro", "cognome": "Novello"}, {"ruolo": "Segretario", "nome": "Giulia", "cognome": "Mitri"}, {"ruolo": "Tesoriere", "nome": "Stefano", "cognome": "Nonini"}, {"ruolo": "Presidente di Sezione", "nome": "Edi", "cognome": "Pezzarini"}, {"ruolo": "Consigliere", "nome": "Stefano", "cognome": "Nonini"}, {"ruolo": "Consigliere", "nome": "Giuseppe", "cognome": "Vezil"}]
A79: 9222013 | B79: SEZ. MOGGIO UDINESE | C79: FRIULI-VENEZIA GIULIA | D79: UD | E79: 1948 | F79: 373 | H79: moggioudinese@cai.it | I79: 0 | J79: 0 | K79: 0 | L79: moggioudinese@pec.cai.it | M79: Via Arturo Zardini 1, 33015 MOGGIO UDINESE (UD) | N79: Elena Tavella | O79: [{"ruolo": "Presidente di Sezione", "nome": "Elena", "cognome": "Tavella"}, {"ruolo": "Consigliere", "nome": "Flavio", "cognome": "Gamberini"}, {"ruolo": "Segretario", "nome": "Gianfranco", "cognome": "Druidi"}, {"ruolo": "Vicepresidente", "nome": "Michele", "cognome": "Cimenti"}, {"ruolo": "Delegato Elettivo", "nome": "Michele", "cognome": "Cimenti"}] | P79: APS - ETS | Q79: No
A80: 9222012 | B80: SEZ. MONFALCONE | C80: FRIULI-VENEZIA GIULIA | D80: GO | E80: 1947 | F80: 603 | G80: www.caimonfalcone.org | H80: monfalcone@cai.it | I80: 0481 480292 | L80: monfalcone@pec.cai.it | M80: MARCO POLO 7, 34074 MONFALCONE (GO) | N80: Andrea Miniussi | O80: [{"ruolo": "Consigliere", "nome": "Marco", "cognome": "Bianco"}, {"ruolo": "Consigliere", "nome": "Fabio", "cognome": "Vescovi"}, {"ruolo": "Consigliere", "nome": "Anna", "cognome": "Fasan"}, {"ruolo": "Tesoriere", "nome": "Anna", "cognome": "Fasan"}, {"ruolo": "Delegato Elettivo", "nome": "Andrea", "cognome": "Vescovo"}, {"ruolo": "Presidente di Sezione", "nome": "Andrea", "cognome": "Miniussi"}, {"ruolo": "Vicepresidente", "nome": "Stefano", "cognome": "Fasan"}] | R80: Sì
A81: 9222023 | B81: SEZ. PONTEBBA | C81: FRIULI-VENEZIA GIULIA | D81: UD | E81: 1983 | F81: 209 | H81: pontebba@cai.it | I81: 0 | K81: 93003810301 | L81: pontebba@pec.cai.it | M81: Piazza del Popolo C.P. 57 13, 33016 PONTEBBA (UD) | N81: Rita Di Biasio | O81: [{"ruolo": "Presidente di Sezione", "nome": "Rita", "cognome": "Di Biasio"}] | P81: APS - ETS | Q81: Sì
A82: 9222006 | B82: SEZ. PORDENONE | C82: FRIULI-VENEZIA GIULIA | D82: PN | E82: 1925 | F82: 1787 | G82: www.caipordenone.it | H82: info@cai.pordenone.it | I82: 0434522383 | K82: 80000810939 | L82: pordenone@pec.cai.it | M82: PIAZZA DEL CRISTO 5/A, 33170 PORDENONE (PN) | N82: Alleris Pizzut | O82: [{"ruolo": "Consigliere", "nome": "Alessandro", "cognome": "Miot"}, {"ruolo": "Presidente di Sezione", "nome": "Alleris", "cognome": "Pizzut"}, {"ruolo": "Consigliere", "nome": "Andrea", "cognome": "Gerometta"}, {"ruolo": "Delegato Elettivo", "nome": "Federico", "cognome": "Lenarduzzi"}, {"ruolo": "Vicepresidente", "nome": "Francesca", "cognome": "Infurnari"}, {"ruolo": "Consigliere", "nome": "Franco", "cognome": "Protani"}, {"ruolo": "Consigliere", "nome": "Gianpaolo", "cognome": "Fornasier"}, {"ruolo": "Consigliere", "nome": "Giorgio", "cognome": "Moretti"}, {"ruolo": "Delegato Elettivo", "nome": "Laura", "cognome": "Giust"}, {"ruolo": "Consigliere", "nome": "Leonardo", "cognome": "Marini"}, {"ruolo": "Delegato Elettivo", "nome": "Luigi", "cognome": "Brusadin"}, {"ruolo": "Consigliere", "nome": "Alberto", "cognome": "Magro"}, {"ruolo": "Delegato Elettivo", "nome": "Maria", "cognome": "Orenti"}, {"ruolo": "Tesoriere", "nome": "Roberta", "cognome": "Milani"}, {"ruolo": "Consigliere", "nome": "Roberto", "cognome": "Faggian"}, {"ruolo": "Consigliere", "nome": "Valter", "cognome": "Ceschin"}] | P82: APS - ETS | Q82: No
A83: 9222020 | B83: SEZ. RAVASCLETTO | C83: FRIULI-VENEZIA GIULIA | D83: UD | E83: 1980 | F83: 793 | G83: www.cairavascletto.it | H83: ravascletto@cai.it | I83: 0433 66018 | J83: 93000280300 | L83: ravascletto@pec.cai.it | M83: Via Valcalda C/O BAR PACE ALPINA 13, 33020 RAVASCLETTO (UD) | N83: Alessandro Plozner | O83: [{"ruolo": "Consigliere", "nome": "Lina", "cognome": "Blanzan"}, {"ruolo": "Consigliere", "nome": "Davide", "cognome": "Nodale"}, {"ruolo": "Delegato Elettivo", "nome": "Enrico", "cognome": "Cavalieri"}, {"ruolo": "Delegato Elettivo", "nome": "Francesco", "cognome": "Timeus"}, {"ruolo": "Consigliere", "nome": "Rudy", "cognome": "Primus"}, {"ruolo": "Presidente di Sezione", "nome": "Alessandro", "cognome": "Plozner"}] | P83: APS - ETS | Q83: Sì | R83: Sì
A84: 9222003 | B84: SEZ. S.A.F.- UDINE | C84: FRIULI-VENEZIA GIULIA | D84: UD | E84: 1874 | F84: 2860 | H84: udinesaf@cai.it | I84: 0432 504290 | J84: 00670520303 | K84: 80001930306 | L84: saf@pec.cai.it | M84: VIA BRIGATA RE 29, 33100 UDINE (UD) | N84: Umberto Sello | O84: [{"ruolo": "Consigliere", "nome": "Aldo", "cognome": "Scalettaris"}, {"ruolo": "Consigliere", "nome": "Daniele", "cognome": "Scodeller"}, {"ruolo": "Delegato Elettivo", "nome": "Daniele", "cognome": "Scodeller"}, {"ruolo": "Consigliere", "nome": "Deni", "cognome": "Tomat"}, {"ruolo": "Delegato Elettivo", "nome": "Elsa", "cognome": "De Vecchi"}, {"ruolo": "Tesoriere", "nome": "Ivana", "cognome": "Beltrame"}, {"ruolo": "Delegato Elettivo", "nome": "Emanuele", "cognome": "Rugo"}, {"ruolo": "Consigliere", "nome": "Emanuele", "cognome": "Rugo"}, {"ruolo": "Consigliere", "nome": "Livio", "cognome": "De Marchi"}, {"ruolo": "Delegato Elettivo", "nome": "Livio", "cognome": "De Marchi"}, {"ruolo": "Consigliere", "nome": "Marco", "cognome": "Cabbai"}, {"ruolo": "Delegato Elettivo", "nome": "Marco", "cognome": "Cabbai"}, {"ruolo": "Delegato Elettivo", "nome": "Stefano Dante", "cognome": "Barachino"}, {"ruolo": "Presidente di Sezione", "nome": "Umberto", "cognome": "Sello"}] | P84: ODV - ETS | Q84: No | R84: Sì
A85: 9222001 | B85: SEZ. S.A.G.- TRIESTE | C85: FRIULI-VENEZIA GIULIA | D85: TS | E85: 1883 | F85: 2090 | G85: www.caisag.ts.it | H85: triestesag@cai.it | I85: 040630464 | J85: 00243240322 | K85: 80016540322 | L85: triestesag@pec.cai.it | M85: Via di Donota C.P.1382 TS3 2, 34121 TRIESTE (TS) | N85: Massimiliano Reiter | O85: [{"ruolo": "Delegato Elettivo", "nome": "Paolo", "cognome": "Toffanin"}, {"ruolo": "Delegato Elettivo", "nome": "Chiara", "cognome": "Pavan"}, {"ruolo": "Delegato Elettivo", "nome": "Federica", "cognome": "Lippi"}, {"ruolo": "Delegato Elettivo", "nome": "Guido", "cognome": "Comar"}, {"ruolo": "Presidente di Sezione", "nome": "Massimiliano", "cognome": "Reiter"}] | P85: APS - ETS | Q85: Sì
A86: 9222019 | B86: SEZ. S.VITO AL TAGLIAMENTO | C86: FRIULI-VENEZIA GIULIA | D86: PN | E86: 1969 | F86: 569 | H86: s.vitoaltagliamento@cai.it | I86: 0434 876521 | J86: 01227400932 | K86: 80006820932 | L86: sanvitoaltagliamento@pec.cai.it | M86: DELLO SPORT 1, 33078 SAN VITO AL TAGLIAMENTO (PN) | N86: Giampietro Polesel | O86: [{"ruolo": "Vicepresidente", "nome": "Andrea", "cognome": "Uaran"}, {"ruolo": "Consigliere", "nome": "Giovanni", "cognome": "Cappena"}, {"ruolo": "Consigliere", "nome": "Daniele", "cognome": "Colussi"}, {"ruolo": "Tesoriere", "nome": "Ezio", "cognome": "Campagnolo"}, {"ruolo": "Consigliere", "nome": "Ezio", "cognome": "Campagnolo"}, {"ruolo": "Revisore dei conti", "nome": "Federico", "cognome": "Furlanetto"}, {"ruolo": "Consigliere", "nome": "Francesca", "cognome": "Nadalin"}, {"ruolo": "Revisore dei conti", "nome": "Graziano", "cognome": "Venudo"}, {"ruolo": "Revisore dei conti", "nome": "Ilario", "cognome": "Morettin"}, {"ruolo": "Presidente di Sezione", "nome": "Giampietro", "cognome": "Polesel"}, {"ruolo": "Consigliere", "nome": "Piervito", "cognome": "Caporusso"}, {"ruolo": "Delegato Elettivo", "nome": "Dora Lisa", "cognome": "Rosalen"}, {"ruolo": "Consigliere", "nome": "Renzo", "cognome": "Schiabel"}, {"ruolo": "Consigliere", "nome": "Massimiliano", "cognome": "Zamparutti"}] | P86: APS - ETS | Q86: No
A87: 9222024 | B87: SEZ. SACILE | C87: FRIULI-VENEZIA GIULIA | D87: PN | E87: 1983 | F87: 730 | G87: https://organizzazione.cai.it/sez-sacile/ | H87: sacile@cai.it | I87: 3391617180 | K87: 91001910933 | L87: sacile@pec.cai.it | M87: SAN GIOVANNI DEL TEMPIO 45/I, 33077 SACILE (PN) | N87: Giovanni Nieddu | O87: [{"ruolo": "Revisore dei conti", "nome": "Alessandro", "cognome": "Nadal"}, {"ruolo": "Consigliere", "nome": "Daniele", "cognome": "Ardengo"}, {"ruolo": "Consigliere", "nome": "Luca", "cognome": "Borin"}, {"ruolo": "Delegato Elettivo", "nome": "David", "cognome": "Borsoi"}, {"ruolo": "Consigliere", "nome": "David", "cognome": "Borsoi"}, {"ruolo": "Revisore dei conti", "nome": "Davide", "cognome": "Chies"}, {"ruolo": "Revisore dei conti", "nome": "Paola", "cognome": "Zoppe'"}, {"ruolo": "Presidente di Sezione", "nome": "Giovanni", "cognome": "Nieddu"}, {"ruolo": "Consigliere", "nome": "Giovanni", "cognome": "Zava"}, {"ruolo": "Consigliere", "nome": "Gabriele", "cognome": "Costella"}, {"ruolo": "Consigliere", "nome": "Loredana", "cognome": "Barresi"}, {"ruolo": "Consigliere", "nome": "Elisabetta", "cognome": "Magrini"}, {"ruolo": "Segretario", "nome": "Elisabetta", "cognome": "Magrini"}, {"ruolo": "Vicepresidente", "nome": "Luigi", "cognome": "Spadotto"}, {"ruolo": "Consigliere", "nome": "Luigi", "cognome": "Spadotto"}, {"ruolo": "Tesoriere", "nome": "Luigi", "cognome": "Spadotto"}, {"ruolo": "Consigliere", "nome": "Maurizio", "cognome": "Martin"}, {"ruolo": "Consigliere", "nome": "Pierpaolo", "cognome": "Bottos"}]
A88: 9220033 | B88: SEZ. SAPPADA | C88: FRIULI-VENEZIA GIULIA | D88: UD | E88: 1954 | F88: 472 | G88: organizzazione.cai.it/sez-sappada/ | H88: sappada@cai.it | I88: 3403082230 | J88: 00866210255 | K88: 92000200250 | L88: sappada@pec.cai.it | M88: stadio del fondo - borgata Kratten snc, 33012 SAPPADA (UD) | N88: Dario Piller | O88: [{"ruolo": "Segretario", "nome": "Andrea", "cognome": "Piller"}, {"ruolo": "Delegato Elettivo", "nome": "Andrea", "cognome": "Piller"}, {"ruolo": "Vicepresidente", "nome": "Simone", "cognome": "Pachner"}, {"ruolo": "Presidente di Sezione", "nome": "Dario", "cognome": "Piller"}] | R88: Sì
A89: 9222018 | B89: SEZ. SPILIMBERGO | C89: FRIULI-VENEZIA GIULIA | D89: PN | E89: 1972 | F89: 552 | H89: spilimbergo@cai.it | I89: -------- | K89: 90008620933 | L89: spilimbergo@pec.cai.it | M89: CIRIANI C.P.83 6, 33097 SPILIMBERGO (PN) | N89: Giancarlo Martina | O89: [{"ruolo": "Responsabile di segreteria", "nome": "Chiara", "cognome": "Guadagnin"}, {"ruolo": "Consigliere", "nome": "Chiara", "cognome": "Guadagnin"}, {"ruolo": "Consigliere", "nome": "Enrica", "cognome": "Cominotto"}, {"ruolo": "Consigliere", "nome": "Enrico", "cognome": "Artini"}, {"ruolo": "Presidente di Sezione", "nome": "Giancarlo", "cognome": "Martina"}, {"ruolo": "Consigliere", "nome": "Giovanni", "cognome": "Cesare"}, {"ruolo": "Consigliere", "nome": "Mauro", "cognome": "Biasetti"}, {"ruolo": "Consigliere", "nome": "Luigi", "cognome": "Petrucco"}, {"ruolo": "Delegato Elettivo", "nome": "Antonio", "cognome": "De Paoli"}]
A90: 9222010 | B90: SEZ. TARVISIO | C90: FRIULI-VENEZIA GIULIA | D90: UD | E90: 1946 | F90: 310 | H90: tarvisio@cai.it | I90: 3381661432 | J90: 01628570309 | K90: 84007400306 | L90: tarvisio@pec.cai.it | M90: via degli Alpini C/O EX SEDE VIGILI DEL FUOCO 15, 33018 TARVISIO (UD) | N90: Massimo Rossetto | O90: [{"ruolo": "Presidente di Sezione", "nome": "Massimo", "cognome": "Rossetto"}, {"ruolo": "Delegato Elettivo", "nome": "Maurizio", "cognome": "Bait"}, {"ruolo": "Vicepresidente", "nome": "Pietro", "cognome": "Del Negro"}] | R90: Sì
A91: 9222002 | B91: SEZ. TOLMEZZO | C91: FRIULI-VENEZIA GIULIA | D91: UD | E91: 1967 | F91: 834 | H91: tolmezzo@cai.it | I91: 0433466446 | K91: 84004770305 | L91: tolmezzo@pec.cai.it | M91: VAL DI GORTO 19, 33028 TOLMEZZO (UD) | N91: Pietro De Faccio | O91: [{"ruolo": "Delegato Elettivo", "nome": "Alessandro", "cognome": "Benzoni"}, {"ruolo": "Tesoriere", "nome": "Federico", "cognome": "Scalise"}, {"ruolo": "Vicepresidente", "nome": "Annalisa", "cognome": "Bonfiglioli"}, {"ruolo": "Delegato Elettivo", "nome": "Annalisa", "cognome": "Bonfiglioli"}, {"ruolo": "Presidente di Sezione", "nome": "Pietro", "cognome": "De Faccio"}, {"ruolo": "Segretario", "nome": "Vittorino", "cognome": "Rossitti"}]
A92: 9222029 | B92: SEZ. TRICESIMO | C92: FRIULI-VENEZIA GIULIA | D92: UD | E92: 2019 | F92: 236 | G92: https://organizzazione.cai.it/sez-tricesimo | H92: tricesimo@cai.it | I92: presidente +39 348 981 5243 | L92: tricesimo@pec.cai.it | M92: piazza San Giovanni Bosco snc, 33019 Tricesimo (UD) | N92: Carlo Pontoni | O92: [{"ruolo": "Tesoriere", "nome": "Maria Cristina", "cognome": "Masarotti"}, {"ruolo": "Segretario", "nome": "Daniele", "cognome": "Gomboso"}, {"ruolo": "Consigliere", "nome": "Daniele", "cognome": "Gomboso"}, {"ruolo": "Revisore dei conti", "nome": "Germana", "cognome": "Comelli"}, {"ruolo": "Consigliere", "nome": "Laura", "cognome": "Candotti"}, {"ruolo": "Revisore dei conti", "nome": "Luciano", "cognome": "Patriarca"}, {"ruolo": "Consigliere", "nome": "Marcello", "cognome": "Ciancio"}, {"ruolo": "Vicepresidente", "nome": "Marcello", "cognome": "Ciancio"}, {"ruolo": "Revisore dei conti", "nome": "Michela", "cognome": "D'Angelo"}, {"ruolo": "Consigliere", "nome": "Carlo", "cognome": "Pontoni"}, {"ruolo": "Presidente di Sezione", "nome": "Carlo", "cognome": "Pontoni"}, {"ruolo": "Consigliere", "nome": "Cristina", "cognome": "Sommaro"}]
A93: 9222028 | B93: SEZ. VAL NATISONE | C93: FRIULI-VENEZIA GIULIA | D93: UD | E93: 2016 | F93: 247 | G93: organizzazione.cai.it/sez-val-natisone/ | H93: cai.valnatisone@libero.it | I93: 349 298 3555 | L93: valnatisone@pec.cai.it | M93: Via Alpe Adria 90, 33049 San Pietro al Natisone (UD) | N93: Luca Poiana | O93: [{"ruolo": "Presidente di Sezione", "nome": "Luca", "cognome": "Poiana"}] | R93: Sì
A94: 9222011 | B94: SEZ. XXX OTTOBRE | C94: FRIULI-VENEZIA GIULIA | D94: TS | E94: 1940 | F94: 1602 | H94: xxxottobre@cai.it | I94: 040635500 | J94: 00779400324 | K94: 80017010325 | L94: xxxottobre@pec.cai.it | M94: Via Cesare Battisti 22, 34125 Trieste (TS) | N94: Maurizio De Angelis | O94: [{"ruolo": "Revisore dei conti", "nome": "Alessandro", "cognome": "Mitri"}, {"ruolo": "Consigliere", "nome": "Enzo", "cognome": "Alessio"}, {"ruolo": "Revisore dei conti", "nome": "Marco", "cognome": "Milani"}, {"ruolo": "Presidente di Sezione", "nome": "Maurizio", "cognome": "De Angelis"}, {"ruolo": "Revisore dei conti", "nome": "Elisabetta", "cognome": "Mazzaroli Bullo"}, {"ruolo": "Revisore dei conti", "nome": "Elisabetta", "cognome": "Mazzaroli Bullo"}, {"ruolo": "Responsabile di segreteria", "nome": "Erika", "cognome": "Ratmann"}, {"ruolo": "Responsabile di segreteria", "nome": "Erika", "cognome": "Ratmann"}, {"ruolo": "Consigliere", "nome": "Fulvio", "cognome": "Lachi"}, {"ruolo": "Delegato Elettivo", "nome": "Fulvio", "cognome": "Lachi"}, {"ruolo": "Consigliere", "nome": "Franco", "cognome": "Pettenati"}, {"ruolo": "Delegato Elettivo", "nome": "Giorgio", "cognome": "Godina"}, {"ruolo": "Consigliere", "nome": "Giorgio", "cognome": "Godina"}, {"ruolo": "Consigliere", "nome": "Ilaria", "cognome": "Garofolo"}, {"ruolo": "Consigliere", "nome": "Nadir Luigi", "cognome": "Pieri"}, {"ruolo": "Delegato Elettivo", "nome": "Maria Assunta", "cognome": "Renna"}, {"ruolo": "Vicepresidente", "nome": "Maria Assunta", "cognome": "Renna"}, {"ruolo": "Consigliere", "nome": "Maurizio", "cognome": "Toscano"}, {"ruolo": "Consigliere", "nome": "Piero", "cognome": "Mozzi"}, {"ruolo": "Consigliere", "nome": "Patrizia", "cognome": "Ferrari Frangipani"}, {"ruolo": "Vicepresidente", "nome": "Tullio", "cognome": "Ranni"}] | R94: Sì
A95: 9232010 | B95: SEZ. ALATRI | C95: LAZIO | D95: FR | E95: 1980 | F95: 206 | H95: alatri@cai.it | I95: 393 0697860 | L95: alatri@pec.cai.it | M95: Via dei Manni 10, 03011 ALATRI (FR) | N95: Silvio Campoli | O95: [{"ruolo": "Consigliere", "nome": "Antonella", "cognome": "La Candia"}, {"ruolo": "Consigliere", "nome": "Calogero", "cognome": "Aulicino"}, {"ruolo": "Presidente di Sezione", "nome": "Silvio", "cognome": "Campoli"}, {"ruolo": "Consigliere", "nome": "Edoardo", "cognome": "Cianfrocca"}, {"ruolo": "Consigliere", "nome": "Eleonora", "cognome": "Minnucci"}, {"ruolo": "Vicepresidente", "nome": "Francesca", "cognome": "Sabellico"}, {"ruolo": "Consigliere", "nome": "Marco", "cognome": "Todini"}] | P95: Avviata procedura di iscrizione
A96: 9232019 | B96: SEZ. AMATRICE | C96: LAZIO | D96: RI | E96: 1995 | F96: 215 | G96: http://www.caiamatrice.it/ | H96: sezione@caiamatrice.it | I96: 375 1095438 | K96: 90036980572 | L96: amatrice@pec.cai.it | M96: Viale Saturnino Muzii C/o Casa della Montagna snc, 02012 AMATRICE (RI) | N96: Marco Salvetta | O96: [{"ruolo": "Presidente di Sezione", "nome": "Marco", "cognome": "Salvetta"}] | P96: APS - ETS | Q96: No | R96: Sì
A97: 9232020 | B97: SEZ. ANTRODOCO | C97: LAZIO | D97: RI | E97: 2008 | F97: 206 | G97: https://www.caiantrodoco.it | H97: antrodoco@cai.it | I97: 3487491439 | L97: antrodoco@pec.cai.it | M97: Via Savelli 3, 02013 ANTRODOCO (RI) | N97: Giandomenico Cipriani | O97: [{"ruolo": "Presidente di Sezione", "nome": "Giandomenico", "cognome": "Cipriani"}] | R97: Sì
A98: 9232021 | B98: SEZ. APRILIA | C98: LAZIO | D98: LT | E98: 2011 | F98: 252 | G98: https://www.caiaprilia.com | H98: info@caiaprilia.com | I98: +39 392 641 9503 | K98: 91121850597 | L98: aprilia@pec.cai.it | M98: CARLO CATTANEO 2, 04011 APRILIA (LT) | N98: Roberto Rocca | O98: [{"ruolo": "Delegato Elettivo", "nome": "Paolo", "cognome": "Degli Schiavi"}, {"ruolo": "Presidente di Sezione", "nome": "Roberto", "cognome": "Rocca"}] | P98: APS - ETS | Q98: No
A99: 9232009 | B99: SEZ. CASSINO | C99: LAZIO | D99: FR | E99: 1975 | F99: 356 | G99: www.caicassino.it | H99: cassino@cai.it | I99: 3387058240 (Presidente) | K99: 90021200606 | L99: cassino@pec.cai.it | M99: Via Verdi P.co Baden Powell 23, 03043 CASSINO (FR) | N99: Pietro Miele | O99: [{"ruolo": "Revisore dei conti", "nome": "Luca", "cognome": "Figliolini"}, {"ruolo": "Consigliere", "nome": "Domenico", "cognome": "Capodanno"}, {"ruolo": "Vicepresidente", "nome": "Diego", "cognome": "Magliocchetti"}, {"ruolo": "Consigliere", "nome": "Giovanni", "cognome": "Cristaldi"}, {"ruolo": "Segretario", "nome": "Giuseppe", "cognome": "Giardinelli"}, {"ruolo": "Consigliere", "nome": "Paolo", "cognome": "Rocca"}, {"ruolo": "Tesoriere", "nome": "Pietro", "cognome": "Miele"}, {"ruolo": "Presidente di Sezione", "nome": "Pietro", "cognome": "Miele"}, {"ruolo": "Consigliere", "nome": "Nazzareno", "cognome": "Tomassi"}, {"ruolo": "Revisore dei conti", "nome": "Giampaolo", "cognome": "Pagliari"}, {"ruolo": "Delegato Elettivo", "nome": "Pasqualino", "cognome": "Leone"}, {"ruolo": "Revisore dei conti", "nome": "Pierluigi", "cognome": "Di Vizio"}, {"ruolo": "Consigliere", "nome": "Giuseppe", "cognome": "Valente"}, {"ruolo": "Consigliere", "nome": "Rocco", "cognome": "Esposito"}]
A100: 9232018 | B100: SEZ. COLLEFERRO | C100: LAZIO | D100: RM | E100: 1995 | F100: 288 | G100: caicolleferro.it/ | H100: colleferro@cai.it | I100: 348 7365357 | K100: 95011070588 | L100: colleferro@pec.cai.it | M100: ALFREDO NOBEL C.P. 47, 00034 COLLEFERRO (RM) | N100: Renzo Cellitti | O100: [{"ruolo": "Consigliere", "nome": "Alfredo", "cognome": "Riccioni"}, {"ruolo": "Consigliere", "nome": "Daniela", "cognome": "Venditti"}, {"ruolo": "Consigliere", "nome": "Enrico", "cognome": "Ciullini"}, {"ruolo": "Delegato Elettivo", "nome": "Giuseppe", "cognome": "Giordano"}, {"ruolo": "Consigliere", "nome": "Luca", "cognome": "Valenzi"}, {"ruolo": "Tesoriere", "nome": "Luca", "cognome": "Valenzi"}, {"ruolo": "Vicepresidente", "nome": "Lucia", "cognome": "Rossi"}, {"ruolo": "Vicepresidente", "nome": "Lucia", "cognome": "Rossi"}, {"ruolo": "Presidente di Sezione", "nome": "Renzo", "cognome": "Cellitti"}, {"ruolo": "Consigliere", "nome": "Roberto", "cognome": "Ruggeri"}] | R100: Sì
...

Sheet Sottosezioni
A1: codice | B1: nominativo | C1: sezione | D1: codice sezione | E1: regione | F1: provincia | G1: email | H1: indirizzo
A2: 9101002 | B2: GRUPPO CENTRALE C.A.A.I. | C2: SEZ. C.A.A.I. | D2: 9200001 | E2: EXTRA REGIONE | F2: MI | H2: Via E. Petrella 19, 20124 Milano (MI)
A3: 9101001 | B3: GRUPPO OCCIDENTALE C.A.A.I. | C3: SEZ. C.A.A.I. | D3: 9200001 | E3: EXTRA REGIONE | F3: TO | H3: Via Barbaroux 1, 10122 Torino (TO)
A4: 9101003 | B4: GRUPPO ORIENTALE C.A.A.I. | C4: SEZ. C.A.A.I. | D4: 9200001 | E4: EXTRA REGIONE | F4: BZ | H4: Via A. Diaz C/O ROBERTO ROSSIN 35/A, 39100 Bolzano (BZ)
A5: 9102007 | B5: AGAI COLL. ABRUZZO | C5: ASSOC.GUIDE ALPINE ITAL. | D5: 9200002 | E5: EXTRA REGIONE | F5: AQ | H5: Via Silvio Pellico – MAP1 – int B/2 c/o Cittadini Agostino, 67010 PRETURO (AQ)
A6: 9102005 | B6: AGAI COLL. ALTO ADIGE | C6: ASSOC.GUIDE ALPINE ITAL. | D6: 9200002 | E6: EXTRA REGIONE | F6: BZ | H6: Piazza Fiera 1, 39100 BOLZANO (BZ)
A7: 9102013 | B7: AGAI COLL. CAMPANIA | C7: ASSOC.GUIDE ALPINE ITAL. | D7: 9200002 | E7: EXTRA REGIONE | F7: NA | H7: Via S. Vito 151, 80056 ERCOLANO (NA)
A8: 9102011 | B8: AGAI COLL. EMILIA | C8: ASSOC.GUIDE ALPINE ITAL. | D8: 9200002 | E8: EXTRA REGIONE | F8: RE | H8: VIA DEI MILLE C/o Sez. CAI Reggio Emilia 32, 42122 REGGIO EMILIA (RE)
A9: 9102012 | B9: AGAI COLL. FRIULI V. G. | C9: ASSOC.GUIDE ALPINE ITAL. | D9: 9200002 | E9: EXTRA REGIONE | F9: TS | H9: Via Grignano 7, 34151 TRIESTE (TS)
A10: 9102014 | B10: AGAI COLL. LIGURIA | C10: ASSOC.GUIDE ALPINE ITAL. | D10: 9200002 | E10: EXTRA REGIONE | F10: SV | H10: Via Pertica c/o Sede Comunale 29, 17024 FINALE LIGURE (SV)
A11: 9102003 | B11: AGAI COLL. LOMBARDIA | C11: ASSOC.GUIDE ALPINE ITAL. | D11: 9200002 | E11: EXTRA REGIONE | F11: SO | H11: Via De Capitani Masegra 5, 23100 SONDRIO (SO)
A12: 9102009 | B12: AGAI COLL. MARCHE | C12: ASSOC.GUIDE ALPINE ITAL. | D12: 9200002 | E12: EXTRA REGIONE | F12: AP | H12: C.da Fonte Balzana C/O VALLESI MARCO 1, 63026 LAPEDONA (AP)
A13: 9102001 | B13: AGAI COLL. PIEMONTE | C13: ASSOC.GUIDE ALPINE ITAL. | D13: 9200002 | E13: EXTRA REGIONE | F13: TO | G13: segreteria@guidealpinepiemonte.it | H13: Via Palazzo di Città C/o Palazzo Municipale 39, 10059 SUSA (TO)
A14: 9102008 | B14: AGAI COLL. SICILIA | C14: ASSOC.GUIDE ALPINE ITAL. | D14: 9200002 | E14: EXTRA REGIONE | F14: CT | H14: Piazza Vittorio Emanuele 43, 95030 NICOLOSI (CT)
A15: 9102010 | B15: AGAI COLL. TOSCANA | C15: ASSOC.GUIDE ALPINE ITAL. | D15: 9200002 | E15: EXTRA REGIONE | F15: PO | H15: Via Giovanni Bacci c/o Cristiano Virgilio 15, 59100 PRATO (PO)
A16: 9102004 | B16: AGAI COLL. TRENTINO | C16: ASSOC.GUIDE ALPINE ITAL. | D16: 9200002 | E16: EXTRA REGIONE | F16: TN | H16: Vicolo Galasso 19, 38100 TRENTO (TN)
A17: 9102002 | B17: AGAI COLL. VALLE D'AOSTA | C17: ASSOC.GUIDE ALPINE ITAL. | D17: 9200002 | E17: EXTRA REGIONE | F17: AO | H17: Via Monte Emilius 13, 11100 AOSTA (AO)
A18: 9102006 | B18: AGAI COLL. VENETO | C18: ASSOC.GUIDE ALPINE ITAL. | D18: 9200002 | E18: EXTRA REGIONE | F18: BL | H18: Corso Italia 69/A, 32043 CORTINA D’AMPEZZO (BL)
A19: 9110001 | B19: S.SEZ. ARENZANO | C19: SEZ. LIGURE-GENOVA | D19: 9210001 | E19: LIGURIA | F19: GE | G19: cai-arenzano@libero.it | H19: Via Cesare Battisti 3, 16011 Arenzano (GE)
A20: 9110003 | B20: S.SEZ. CORNIGLIANO | C20: SEZ. LIGURE-GENOVA | D20: 9210001 | E20: LIGURIA | F20: GE | G20: cornigliano@cailiguregenova.it | H20: Via Nino Cervetto 40 R, 16152 Genova (GE)
A21: 9110009 | B21: S.SEZ. SORI | C21: SEZ. LIGURE-GENOVA | D21: 9210001 | E21: LIGURIA | F21: GE | G21: sabinastella@stellaeassociati.it | H21: Via Stagno 19, 16031 Sori (GE)
A22: 9110006 | B22: S.SEZ. CENGIO | C22: SEZ. SAVONA | D22: 9210003 | E22: LIGURIA | F22: SV | G22: cai.cengio@libero.it | H22: PIAZZA DELLE SCUOLE 4, 17056 CENGIO GENEPRO (SV)
A23: 9110007 | B23: S.SEZ. VALBORMIDA | C23: SEZ. SAVONA | D23: 9210003 | E23: LIGURIA | F23: SV | G23: cai.valbormida@gmail.com | H23: VIA ROMA (PORTA SOPRANA) 1, 17014 CAIRO MONTENOTTE (SV)
A24: 9110004 | B24: S.SEZ. VAL DI VARA-RIVIERA | C24: SEZ. LA SPEZIA | D24: 9210004 | E24: LIGURIA | F24: SP | H24: Centro Polifunzionale C/O COMUNE DI BRUGNATO, 19020 Brugnato (SP)
A25: 9110008 | B25: S.SEZ. GE-SESTRI (diventata Sezione) | C25: SEZ. U.L.E. GENOVA | D25: 9210005 | E25: LIGURIA | F25: GE | H25: Via Galliano 16/4, 16153 Sestri Ponente (GE)
A26: 9112046 | B26: S.SEZ. C.R.A.L. C.R.T. | C26: SEZ. TORINO | D26: 9212001 | E26: PIEMONTE | F26: TO | H26: Via Nizza 150, 10126 Torino (TO)
A27: 9112020 | B27: S.SEZ. G.E.A.T. | C27: SEZ. TORINO | D27: 9212001 | E27: PIEMONTE | F27: TO | H27: Via Barbaroux 1, 10122 Torino (TO)
A28: 9112023 | B28: S.SEZ. S.U.C.A.I. | C28: SEZ. TORINO | D28: 9212001 | E28: PIEMONTE | F28: TO | H28: Via Barbaroux 1, 10131 Torino (TO)
A29: 9112037 | B29: S.SEZ. SANTENA | C29: SEZ. TORINO | D29: 9212001 | E29: PIEMONTE | F29: TO | H29: Vicolo San Lorenzo 27, 10026 Santena (TO)
A30: 9112022 | B30: S.SEZ. SETTIMO TORINESE | C30: SEZ. TORINO | D30: 9212001 | E30: PIEMONTE | F30: TO | H30: Via Buonarroti C/O Unitre 8/C, 10036 Settimo Torinese (TO)
A31: 9112024 | B31: S.SEZ. U.E.T. | C31: SEZ. TORINO | D31: 9212001 | E31: PIEMONTE | F31: TO | H31: Via Maresciallo Giardino C/O CAI SEDE ESTIVA 48, 10131 Torino (TO)
A32: 9112025 | B32: S.SEZ. ALAGNA | C32: SEZ. VARALLO SESIA | D32: 9212002 | E32: PIEMONTE | F32: VC | G32: alagna@caivarallo.it | H32: VIA CENTRO 1, 13021 ALAGNA VALSESIA (VC)
A33: 9112026 | B33: S.SEZ. BORGOSESIA | C33: SEZ. VARALLO SESIA | D33: 9212002 | E33: PIEMONTE | F33: VC | G33: borgosesia@caivarallo.it | H33: Piazza Mazzini (Palazzo Castellani), 13011 Borgosesia (VC)
A34: 9112027 | B34: S.SEZ. GHEMME | C34: SEZ. VARALLO SESIA | D34: 9212002 | E34: PIEMONTE | F34: NO | G34: ghemme@caivarallo.it | H34: Piazza Castello 23, 28074 Ghemme (NO)
A35: 9112028 | B35: S.SEZ. GRIGNASCO | C35: SEZ. VARALLO SESIA | D35: 9212002 | E35: PIEMONTE | F35: NO | G35: grignasco@caivarallo.it | H35: Via Costantino Perazzi 10, 28075 Grignasco (NO)
A36: 9112029 | B36: S.SEZ. ROMAGNANO | C36: SEZ. VARALLO SESIA | D36: 9212002 | E36: PIEMONTE | F36: NO | G36: romagnano@caivarallo.it | H36: Via Fontana del Frate 8, 28078 Romagnano Sesia (NO)
A37: 9112030 | B37: S.SEZ. SCOPELLO | C37: SEZ. VARALLO SESIA | D37: 9212002 | E37: PIEMONTE | F37: VC | G37: scopello@caivarallo.it | H37: c/o Municipio di Scopello, 13020 SCOPELLO (VC)
A38: 9112040 | B38: S.SEZ. BORGO SAN DALMAZZO | C38: SEZ. CUNEO | D38: 9212006 | E38: PIEMONTE | F38: CN | H38: Via Monsignor Riberi 12, 12011 Borgo San Dalmazzo (CN)
A39: 9112010 | B39: S.SEZ. BUSCA | C39: SEZ. CUNEO | D39: 9212006 | E39: PIEMONTE | F39: CN | H39: Via Pes di Villamarina 5, 12022 Busca (CN)
A40: 9112012 | B40: S.SEZ. DRONERO | C40: SEZ. CUNEO | D40: 9212006 | E40: PIEMONTE | F40: CN | H40: Via Pasubio 5, 12025 Dronero (CN)
A41: 9112011 | B41: S.SEZ. GRUPPO SPELEOLOGICO | C41: SEZ. CUNEO | D41: 9212006 | E41: PIEMONTE | F41: CN | H41: Via Porta Mondovì 5, 12100 Cuneo (CN)
A42: 9112033 | B42: S.SEZ. SPARONE | C42: SEZ. IVREA | D42: 9212008 | E42: PIEMONTE | F42: TO | G42: cai.sparone.1980@gmail.com | H42: Vicolo Faletti 1, 10080 Sparone (TO)
A43: 9112008 | B43: S.SEZ. CIGLIANO | C43: SEZ. CHIVASSO | D43: 9212013 | E43: PIEMONTE | F43: VC | H43: Piazza Alpini, 13043 Cigliano (VC)
A44: 9112039 | B44: S.SEZ. FOGLIZZO | C44: SEZ. CHIVASSO | D44: 9212013 | E44: PIEMONTE | F44: TO | H44: Via Palestro C/O SIG.RA MUSSO CATIA 16, 10090 Foglizzo (TO)
A45: 9112041 | B45: S.SEZ. GASSINO TORINESE | C45: SEZ. CHIVASSO | D45: 9212013 | E45: PIEMONTE | F45: TO | H45: Via Bussolino centro FRAZ.BUSSOLINO ALTO 16, 10090 Gassino Torinese (TO)
A46: 9112009 | B46: S.SEZ. SALUGGIA | C46: SEZ. CHIVASSO | D46: 9212013 | E46: PIEMONTE | F46: VC | H46: Piazza Municipio Centro Settia 10, 13040 Saluggia (VC)
A47: 9112017 | B47: S.SEZ. OLEGGIO MEZZOMERICO | C47: SEZ. NOVARA | D47: 9212014 | E47: PIEMONTE | F47: NO | G47: segreteria.bom@gmail.com | H47: Via Gramsci 79, 28047 Oleggio (NO)
A48: 9112031 | B48: S.SEZ. GATTINARA | C48: SEZ. VERCELLI | D48: 9212016 | E48: PIEMONTE | F48: VC | H48: Via Lamarmora C/O GRUPPO ALP.POZZI 23, 13045 Gattinara (VC)
A49: 9112049 | B49: S.SEZ. TROFARELLO | C49: SEZ. UGET TORINO | D49: 9212019 | E49: PIEMONTE | F49: TO | H49: CORSO FRANCIA 192, 10145 TORINO (TO)
A50: 9112002 | B50: S.SEZ. AVIGLIANA | C50: SEZ. ALPIGNANO | D50: 9212044 | E50: PIEMONTE | F50: TO | H50: Piazza Conte Rosso 11, 10051 Avigliana (TO)
A51: 9112052 | B51: S.SEZ. VAL DI VIU' | C51: SEZ. LANZO TORINESE | D51: 9212047 | E51: PIEMONTE | F51: TO | H51: piazza Schiari 1, 10070 Viù (TO)
A52: 9112050 | B52: S.SEZ. VALGRANDE | C52: SEZ. LANZO TORINESE | D52: 9212047 | E52: PIEMONTE | F52: TO | H52: VIA ROMA C/O PIZZERIA DEGLI AMICI 179, 10070 CANTOIRA (TO)
A53: 9112054 | B53: S.SEZ. SAUZE D'OULX | C53: SEZ. BARDONECCHIA | D53: 9212052 | E53: PIEMONTE | F53: TO | G53: max.perron71@gmail.com | H53: Viale Genevris snc, 10050 Sauze D'Oulx (TO)
A54: 9112051 | B54: S.SEZ. SALBERTRAND | C54: SEZ. COAZZE | D54: 9212063 | E54: PIEMONTE | F54: TO | H54: Piazza Martiri Libertà 1, 10050 Salbertrand (TO)
A55: 9112053 | B55: S.SEZ. CANDIOLO | C55: SEZ. VIGONE | D55: 9212074 | E55: PIEMONTE | F55: TO | G55: caicandiolo@gmail.com | H55: Piazza Riccardo Sella 1, 10060 Candiolo (TO)
A56: 9114002 | B56: S.SEZ. BARTHELEMY | C56: SEZ. AOSTA | D56: 9214001 | E56: VALLE D'AOSTA | F56: AO | G56: segreteria@stb.caivda.it | H56: Via Aosta c/o Municipio 13, 11020 NUS (AO)
A57: 9116142 | B57: S.SEZ. BERBENNO | C57: SEZ. VALTELLINESE-SONDRIO | D57: 9216001 | E57: LOMBARDIA | F57: SO | G57: infocaiberbenno@gmail.com | H57: Via alle Scuole 103, 23010 BERBENNO DI VALTELLINA (SO)
A58: 9116109 | B58: S.SEZ. PONTE IN VALTELLINA | C58: SEZ. VALTELLINESE-SONDRIO | D58: 9216001 | E58: LOMBARDIA | F58: SO | H58: PIAZZA LUINI 10, 23026 PONTE IN VALTELLINA (SO)
A59: 9116143 | B59: S.SEZ. TEGLIO (diventata Sezione) | C59: SEZ. VALTELLINESE-SONDRIO | D59: 9216001 | E59: LOMBARDIA | F59: SO | H59: PIAZZA S. EUFEMIA 7, 23036 TEGLIO (SO)
A60: 9116089 | B60: S.SEZ. TIRANO | C60: SEZ. VALTELLINESE-SONDRIO | D60: 9216001 | E60: LOMBARDIA | F60: SO | H60: VIA GARIBALDI 8, 23037 TIRANO (SO)
A61: 9116140 | B61: S.SEZ. VALDIDENTRO | C61: SEZ. VALTELLINESE-SONDRIO | D61: 9216001 | E61: LOMBARDIA | F61: SO | H61: VIA NAZIONALE 18, 23038 VALDIDENTRO (SO)
A62: 9116003 | B62: S.SEZ. ALBINO | C62: SEZ. BERGAMO | D62: 9216002 | E62: LOMBARDIA | F62: BG | G62: caialbino@caibergamo.it | H62: Via Lover 2, 24021 Albino (BG)
A63: 9116133 | B63: S.SEZ. ALTA VALLE SERIANA | C63: SEZ. BERGAMO | D63: 9216002 | E63: LOMBARDIA | F63: BG | G63: caialtavalleseriana@caibergamo.it | H63: Piazza Monte Grappa 3, 24020 Ardesio (BG)
A64: 9116004 | B64: S.SEZ. ALZANO LOMBARDO | C64: SEZ. BERGAMO | D64: 9216002 | E64: LOMBARDIA | F64: BG | G64: caialzano@caibergamo.it | H64: Via Giorgio Paglia 11, 24022 Alzano Lombardo (BG)
A65: 9116120 | B65: S.SEZ. BRIGNANO GERA D'ADDA | C65: SEZ. BERGAMO | D65: 9216002 | E65: LOMBARDIA | F65: BG | G65: caibrignano@caibergamo.it | H65: Via Carni C/O SCUOLE ELEMENTARI, 24053 Brignano Gera d'Adda (BG)
A66: 9116005 | B66: S.SEZ. CISANO | C66: SEZ. BERGAMO | D66: 9216002 | E66: LOMBARDIA | F66: BG | G66: caicisano@caibergamo.it | H66: Via San Domenico Savio 3/C, 24034 Cisano Bergamasco (BG)
A67: 9116008 | B67: S.SEZ. GAZZANIGA | C67: SEZ. BERGAMO | D67: 9216002 | E67: LOMBARDIA | F67: BG | G67: caigazzaniga@caibergamo.it | H67: Via Europa 23, 24025 Gazzaniga (BG)
A68: 9116009 | B68: S.SEZ. LEFFE | C68: SEZ. BERGAMO | D68: 9216002 | E68: LOMBARDIA | F68: BG | G68: caileffe@caibergamo.it | H68: Piazza Unità d'Italia 3, 24026 Leffe (BG)
A69: 9116010 | B69: S.SEZ. NEMBRO | C69: SEZ. BERGAMO | D69: 9216002 | E69: LOMBARDIA | F69: BG | G69: cainembro@caibergamo.it | H69: VIA GAVARNO 79, 24027 Nembro (BG)
A70: 9116013 | B70: S.SEZ. PONTE SAN PIETRO | C70: SEZ. BERGAMO | D70: 9216002 | E70: LOMBARDIA | F70: BG | G70: caiponte@caibergamo.it | H70: Via Trento e Trieste 8/A, 24036 Ponte San Pietro (BG)
A71: 9116138 | B71: S.SEZ. TRESCORE VALCAVALLINA | C71: SEZ. BERGAMO | D71: 9216002 | E71: LOMBARDIA | F71: BG | G71: caitrescorevalcavallina@caibergamo.it | H71: Via Aldo Moro 35, 24069 Trescore Balneario (BG)
A72: 9116128 | B72: S.SEZ. URGNANO | C72: SEZ. BERGAMO | D72: 9216002 | E72: LOMBARDIA | F72: BG | G72: caiurgnano@caibergamo.it | H72: Via Moneta 17, 24059 Urgnano (BG)
A73: 9116014 | B73: S.SEZ. VAL DI SCALVE | C73: SEZ. BERGAMO | D73: 9216002 | E73: LOMBARDIA | F73: BG | G73: caivaldiscalve@caibergamo.it | H73: Via Acerbis C/O COM.MONTANA DI SCALVE 2, 24020 Vilminore (BG)
... A79: 9116016 | B79: S.SEZ. ZOGNO | C79: SEZ. BERGAMO | D79: 9216002 | E79: LOMBARDIA | F79: BG | G79: caizogno@caibergamo.it | H79: Via XI Febbraio C/O ORATORIO 11, 24019 Zogno (BG)
A80: 9116067 | B80: S.SEZ. CASSA DI RISPARMIO | C80: SEZ. MILANO | D80: 9216003 | E80: LOMBARDIA | F80: MI | H80: Via delle Erbe 2, 20121 Milano (MI)
A81: 9116069 | B81: S.SEZ. COMIT | C81: SEZ. MILANO | D81: 9216003 | E81: LOMBARDIA | F81: MI | H81: Via Silvio Pellico C/O CAI 6, 20121 Milano (MI)
A82: 9116115 | B82: S.SEZ. CORSERA | C82: SEZ. MILANO | D82: 9216003 | E82: LOMBARDIA | F82: MI | H82: Via Cefalù CENTRO SPORTIVO RCS 40, 20151 Milano (MI)
A83: 9116104 | B83: S.SEZ. EDELWEISS | C83: SEZ. MILANO | D83: 9216003 | E83: LOMBARDIA | F83: MI | H83: Via Perugino 13/15, 20135 Milano (MI)
A84: 9116071 | B84: S.SEZ. FALC | C84: SEZ. MILANO | D84: 9216003 | E84: LOMBARDIA | F84: MI | H84: Via Mac Mahon C/O PARROCCHIA 113, 20155 Milano (MI)
A85: 9116072 | B85: S.SEZ. FIOR DI ROCCIA | C85: SEZ. MILANO | D85: 9216003 | E85: LOMBARDIA | F85: MI | H85: Viale Repubblica Cisalpina Arena Civica e, 20154 Milano (MI)
A86: 9116073 | B86: S.SEZ. G.A.M. | C86: SEZ. MILANO | D86: 9216003 | E86: LOMBARDIA | F86: MI | H86: Via Merlo 3, 20122 Milano (MI)
A87: 9116114 | B87: S.SEZ. G.E.S.A. | C87: SEZ. MILANO | D87: 9216003 | E87: LOMBARDIA | F87: MI | H87: Via Kant 6/8, 20151 Milano (MI)
A88: 9116074 | B88: S.SEZ. GERVASUTTI | C88: SEZ. MILANO | D88: 9216003 | E88: LOMBARDIA | F88: MI | H88: via Duccio di Boninsegna c/o la Sede CAI Milano 21, 20145 Milano (MI)
A89: 9116077 | B89: S.SEZ. MONTEDISON | C89: SEZ. MILANO | D89: 9216003 | E89: LOMBARDIA | F89: MI | H89: Via Silvio Pellico 6, 20121 Milano (MI)
A90: 9116050 | B90: S.SEZ. BALLABIO | C90: SEZ. LECCO | D90: 9216004 | E90: LOMBARDIA | F90: LC | G90: cai.ballabio@tiscali.it | H90: Via Leonardo da Vinci 4, 23811 Ballabio (LC)
A91: 9116051 | B91: S.SEZ. BARZIO | C91: SEZ. LECCO | D91: 9216004 | E91: LOMBARDIA | F91: LC | G91: barzio@cai.lecco.it | H91: Via Roma ex casa comunale 42, 23816 Barzio (LC)
A92: 9116052 | B92: S.SEZ. STRADA STORTA | C92: SEZ. LECCO | D92: 9216004 | E92: LOMBARDIA | F92: LC | G92: info@stradastorta.it | H92: Via Rovereto Acquate 2, 23900 Lecco (LC)
A93: 9116018 | B93: S.SEZ. BAGOLINO | C93: SEZ. BRESCIA | D93: 9216005 | E93: LOMBARDIA | F93: BS | H93: Via 4 Novembre 6, 25072 BAGOLINO (BS)
A94: 9116019 | B94: S.SEZ. CIDNEO O.M. | C94: SEZ. BRESCIA | D94: 9216005 | E94: LOMBARDIA | F94: BS | H94: Via Volturno 62, 25126 Brescia (BS)
A95: 9116110 | B95: S.SEZ. COLLEBEATO | C95: SEZ. BRESCIA | D95: 9216005 | E95: LOMBARDIA | F95: BS | H95: Via Vittorio Veneto C/O ANDREOLI DOMENICO 8, 25060 Collebeato (BS)
A96: 9116023 | B96: S.SEZ. ISEO (diventata Sezione) | C96: SEZ. BRESCIA | D96: 9216005 | E96: LOMBARDIA | F96: BS | H96: Via Duomo 22, 25049 Iseo (BS)
A97: 9116106 | B97: S.SEZ. MANERBIO | C97: SEZ. BRESCIA | D97: 9216005 | E97: LOMBARDIA | F97: BS | H97: Via Palestro CASELLA POSTALE 35 55/B, 25025 Manerbio (BS)
A98: 9116024 | B98: S.SEZ. MARONE | C98: SEZ. BRESCIA | D98: 9216005 | E98: LOMBARDIA | F98: BS | H98: Via Roma, 25054 Marone (BS)
A99: 9116093 | B99: S.SEZ. NAVE | C99: SEZ. BRESCIA | D99: 9216005 | E99: LOMBARDIA | F99: BS | G99: cainave@cai-nave.it | H99: Via Ferruccio Ventura 7, 25075 Nave (BS)
A100: 9116025 | B100: S.SEZ. ODOLO | C100: SEZ. BRESCIA | D100: 9216005 | E100: LOMBARDIA | F100: BS | H100: Via A. Moro C/O SOLAZZI GIAMPIERO 48, 25076 Odolo (BS)
A101: 9116123 | B101: S.SEZ. PROVAGLIO D'ISEO | C101: SEZ. BRESCIA | D101: 9216005 | E101: LOMBARDIA | F101: BS | H101: Via C, Battisti 8, 25050 Provaglio d'Iseo (BS)
A102: 9116029 | B102: S.SEZ. SANTICOLO | C102: SEZ. BRESCIA | D102: 9216005 | E102: LOMBARDIA | F102: BS | H102: Piazza XXIV Maggio 1, 25040 Santicolo (BS)
A103: 9116119 | B103: S.SEZ. BIZZARONE | C103: SEZ. COMO | D103: 9216006 | E103: LOMBARDIA | F103: CO | G103: roncoroni.mario@libero.it | H103: VIA SANTA MARGHERITA C/O CENTRO SPORTIVO 21, 22020 BIZZARONE (CO)
A104: 9116036 | B104: S.SEZ. MASLIANICO | C104: SEZ. COMO | D104: 9216006 | E104: LOMBARDIA | F104: CO | H104: VIA CESARE BATTISTI C/O CENTRO CIVICO 23, 22026 MASLIANICO (CO)
A105: 9116037 | B105: S.SEZ. MONTE OLIMPINO | C105: SEZ. COMO | D105: 9216006 | E105: LOMBARDIA | F105: CO | H105: VIA BELLINZONA 189, 22100 Como (CO)
...

Sheet GR
A1: Nome | B1: Ente del Terzo Settore
A2: CAI GR Abruzzo | B2: Interessato
A3: CAI GR Alto Adige | B3: ETS
A4: CAI GR Basilicata | B4: Non ETS | C4: no risposta
A5: CAI GR Calabria | B5: In fase di iscrizione
A6: CAI GR Campania | B6: In fase di iscrizione
A7: CAI GR Emilia Romagna | B7: ETS
A8: CAI GR Friuli Venezia Giulia | B8: Non ETS
A9: CAI GR Lazio | B9: Non ETS | C9: al momento non interessati ma la questione è ancora in discussione
A10: CAI GR Liguria | B10: ETS
A11: CAI GR Lombardia | B11: Interessato
A12: CAI GR Marche | B12: Interessato | C12: no risposta
A13: CAI GR Molise | B13: Non ETS | C13: no risposta
A14: CAI GR Piemonte | B14: ETS
A15: CAI GR Puglia | B15: In fase di iscrizione | C15: hanno lo statuto bloccato
A16: CAI GR Sardegna | B16: Non ETS | C16: no risposta
A17: CAI GR Sicilia | B17: ETS
A18: CAI GR Toscana | B18: ETS
A19: CAI GR Trentino - SAT | B19: ETS
A20: CAI GR Umbria | B20: Non ETS | C20: non è una loro priorità ma non escludono ancora del tutto
A21: CAI GR Valle D'Aosta | B21: Non ETS
A22: CAI GR Veneto | B22: In fase di iscrizione

Sheet Statistiche Sezioni
B3: Sezioni ETS | C3: %
A4: APS - ETS | B4: =COUNTIF(Sezioni!$P:$P,A4) -> 188 | C4: =B4/B9 -> 0.77366255
A5: ODV - ETS | B5: =COUNTIF(Sezioni!$P:$P,A5) -> 15 | C5: =B5/B9 -> 0.061728395
A6: ETS | B6: =COUNTIF(Sezioni!$P:$P,A6) -> 12 | C6: =B6/B9 -> 0.049382716
A7: Avviata procedura di iscrizione | B7: =COUNTIF(Sezioni!$P:$P,A7) -> 29 | C7: =B7/B9 -> 0.11934156
A9: Sezioni ETS | B9: 243 | C9: =B9/B10 -> 0.46285714
A10: Tootale Sezioni | B10: =525 -> 525
A12: RIEPILOGO PER GR
B13: Sezioni ETS | C13: TOT SEZIONI | D13: % ETS
A14: Abruzzo | B14: =COUNTIFS(Sezioni!$C:$C,A14,Sezioni!$P:$P,"<>") -> 5 | C14: =COUNTIF(Sezioni!$C:$C,A14) -> 24 | D14: =B14/C14 -> 0.20833333
A15: Alto Adige | B15: =COUNTIFS(Sezioni!$C:$C,A15,Sezioni!$P:$P,"<>") -> 12 | C15: =COUNTIF(Sezioni!$C:$C,A15) -> 14 | D15: =B15/C15 -> 0.85714286
A16: Basilicata | B16: =COUNTIFS(Sezioni!$C:$C,A16,Sezioni!$P:$P,"<>") -> 4 | C16: =COUNTIF(Sezioni!$C:$C,A16) -> 4 | D16: =B16/C16 -> 1
A17: Calabria | B17: =COUNTIFS(Sezioni!$C:$C,A17,Sezioni!$P:$P,"<>") -> 5 | C17: =COUNTIF(Sezioni!$C:$C,A17) -> 5 | D17: =B17/C17 -> 1
A18: Campania | B18: =COUNTIFS(Sezioni!$C:$C,A18,Sezioni!$P:$P,"<>") -> 5 | C18: =COUNTIF(Sezioni!$C:$C,A18) -> 9 | D18: =B18/C18 -> 0.55555556
A19: Emilia-Romagna | B19: =COUNTIFS(Sezioni!$C:$C,A19,Sezioni!$P:$P,"<>") -> 20 | C19: =COUNTIF(Sezioni!$C:$C,A19) -> 20 | D19: =B19/C19 -> 1
A20: Friuli-Venezia Giulia | B20: =COUNTIFS(Sezioni!$C:$C,A20,Sezioni!$P:$P,"<>") -> 13 | C20: =COUNTIF(Sezioni!$C:$C,A20) -> 27 | D20: =B20/C20 -> 0.48148148
A21: Lazio | B21: =COUNTIFS(Sezioni!$C:$C,A21,Sezioni!$P:$P,"<>") -> 9 | C21: =COUNTIF(Sezioni!$C:$C,A21) -> 19 | D21: =B21/C21 -> 0.47368421
A22: Liguria | B22: =COUNTIFS(Sezioni!$C:$C,A22,Sezioni!$P:$P,"<>") -> 6 | C22: =COUNTIF(Sezioni!$C:$C,A22) -> 19 | D22: =B22/C22 -> 0.31578947
A23: Lombardia | B23: =COUNTIFS(Sezioni!$C:$C,A23,Sezioni!$P:$P,"<>") -> 49 | C23: =COUNTIF(Sezioni!$C:$C,A23) -> 152 | D23: =B23/C23 -> 0.32236842
A24: Marche | B24: =COUNTIFS(Sezioni!$C:$C,A24,Sezioni!$P:$P,"<>") -> 5 | C24: =COUNTIF(Sezioni!$C:$C,A24) -> 15 | D24: =B24/C24 -> 0.33333333
A25: Molise | B25: =COUNTIFS(Sezioni!$C:$C,A25,Sezioni!$P:$P,"<>") -> 1 | C25: =COUNTIF(Sezioni!$C:$C,A25) -> 2 | D25: =B25/C25 -> 0.5
... A34: Veneto | B34: =COUNTIFS(Sezioni!$C:$C,A34,Sezioni!$P:$P,"<>") -> 36 | C34: =COUNTIF(Sezioni!$C:$C,A34) -> 65 | D34: =B34/C34 -> 0.55384615
B36: =SUM(B14:B34) -> 244 | C36: =SUM(C14:C34) -> 525 | D36: =B36/C36 -> 0.4647619
A39: GRUPPI REGIONALI | B39: GR ETS | C39: %
A40: ETS | B40: =COUNTIF(GR!$B:$B,A40) -> 7 | C40: =B40/B45 -> 0.33333333
A41: In fase di iscrizione | B41: =COUNTIF(GR!$B:$B,A41) -> 4 | C41: =B41/B45 -> 0.19047619
A42: Interessato | B42: =COUNTIF(GR!$B:$B,A42) -> 3 | C42: =B42/B45 -> 0.14285714
A43: NON ETS | B43: =COUNTIF(GR!$B:$B,A43) -> 7 | C43: =B43/B45 -> 0.33333333
B45: =SUM(B40:B43) -> 21
